{
	"animations": [
		{
			"offsets": [
				-30,
				-90
			],
			"loop": false,
			"fps": 24,
			"anim": "idle",
			"indices": [],
			"name": "Ellie Idle"
		},
		{
			"offsets": [
				214,
				-105
			],
			"loop": false,
			"fps": 24,
			"anim": "singLEFT",
			"indices": [],
			"name": "Ellie Left"
		},
		{
			"offsets": [
				-80,
				-151
			],
			"loop": false,
			"fps": 24,
			"anim": "singDOWN",
			"indices": [],
			"name": "Ellie Down"
		},
		{
			"offsets": [
				-91,
				-39
			],
			"loop": false,
			"fps": 24,
			"anim": "singUP",
			"indices": [],
			"name": "Ellie Up"
		},
		{
			"offsets": [
				-39,
				-30
			],
			"loop": false,
			"fps": 24,
			"anim": "singRIGHT",
			"indices": [],
			"name": "Ellie Right"
		},
		{
			"offsets": [
				-30,
				973
			],
			"loop": false,
			"fps": 24,
			"anim": "enter",
			"indices": [],
			"name": "Ellie Enter Animation"
		}
	],
	"no_antialiasing": false,
	"image": "characters/Ellie_Assets",
	"position": [
		-30,
		30
	],
	"healthicon": "ellie",
	"flip_x": false,
	"healthbar_colors": [
		255,
		255,
		255
	],
	"camera_position": [
		-260,
		110
	],
	"sing_duration": 6.1,
	"scale": 1
}