{
	"animations": [
		{
			"offsets": [
				-157,
				-441
			],
			"loop": false,
			"fps": 24,
			"anim": "singRIGHT",
			"indices": [],
			"name": "Right"
		},
		{
			"offsets": [
				11,
				-455
			],
			"loop": false,
			"fps": 24,
			"anim": "singDOWN",
			"indices": [],
			"name": "Down"
		},
		{
			"offsets": [
				180,
				-228
			],
			"loop": false,
			"fps": 24,
			"anim": "singUP",
			"indices": [],
			"name": "Up"
		},
		{
			"offsets": [
				10,
				-354
			],
			"loop": false,
			"fps": 24,
			"anim": "singLEFT",
			"indices": [],
			"name": "Left"
		},
		{
			"offsets": [
				70,
				-280
			],
			"indices": [],
			"fps": 24,
			"anim": "idle",
			"loop": true,
			"name": "Idle"
		}
	],
	"no_antialiasing": false,
	"image": "characters/redMungParasite",
	"position": [
		-380,
		-450
	],
	"healthicon": "redmungus",
	"flip_x": false,
	"healthbar_colors": [
		255,
		51,
		51
	],
	"camera_position": [
		-130,
		300
	],
	"sing_duration": 6.1,
	"scale": 1
}