{
	"animations": [
		{
			"offsets": [
				-30,
				-90
			],
			"loop": false,
			"fps": 24,
			"anim": "idle",
			"indices": [],
			"name": "WIdle"
		},
		{
			"offsets": [
				-17,
				-89
			],
			"loop": false,
			"fps": 24,
			"anim": "singLEFT",
			"indices": [],
			"name": "WLeft"
		},
		{
			"offsets": [
				-73,
				-111
			],
			"loop": false,
			"fps": 24,
			"anim": "singDOWN",
			"indices": [],
			"name": "WDown"
		},
		{
			"offsets": [
				-84,
				-64
			],
			"loop": false,
			"fps": 24,
			"anim": "singUP",
			"indices": [],
			"name": "WUp"
		},
		{
			"offsets": [
				-81,
				-72
			],
			"loop": false,
			"fps": 24,
			"anim": "singRIGHT",
			"indices": [],
			"name": "WRight"
		},
		{
			"offsets": [
				-73,
				-111
			],
			"indices": [
				4,
				5,
				6,
				7
			],
			"fps": 24,
			"anim": "singDOWN-loop",
			"loop": true,
			"name": "WDown"
		},
		{
			"offsets": [
				-84,
				-64
			],
			"indices": [
				4,
				5,
				6,
				7
			],
			"fps": 24,
			"anim": "singUP-loop",
			"loop": true,
			"name": "WUp"
		},
		{
			"offsets": [
				-17,
				-89
			],
			"indices": [
				4,
				5,
				6,
				7
			],
			"fps": 24,
			"anim": "singLEFT-loop",
			"loop": true,
			"name": "WLeft"
		},
		{
			"offsets": [
				-81,
				-72
			],
			"indices": [
				4,
				5,
				6,
				7
			],
			"fps": 24,
			"anim": "singRIGHT-loop",
			"loop": true,
			"name": "WRight"
		}
	],
	"no_antialiasing": false,
	"image": "characters/warchief",
	"position": [
		-120,
		190
	],
	"healthicon": "warchief",
	"flip_x": false,
	"healthbar_colors": [
		113,
		15,
		175
	],
	"camera_position": [
		110,
		140
	],
	"sing_duration": 6.1,
	"scale": 1
}