<?xml version="1.0" encoding="utf-8"?>
<TextureAtlas imagePath="portraits.png">
	<!-- Created with Adobe Animate version 22.0.2.168 -->
	<!-- http://www.adobe.com/products/animate.html -->
	<SubTexture name="Character0000" x="2616" y="2844" width="812" height="812" frameX="-155" frameY="-112" frameWidth="1215" frameHeight="1097"/>
	<SubTexture name="Character0001" x="3" y="2847" width="812" height="812" frameX="-155" frameY="-112" frameWidth="1215" frameHeight="1097"/>
	<SubTexture name="Character0002" x="4666" y="1910" width="921" height="920" frameX="-121" frameY="-32" frameWidth="1215" frameHeight="1097"/>
	<SubTexture name="Character0003" x="3739" y="2837" width="833" height="833" frameX="-143" frameY="-104" frameWidth="1215" frameHeight="1097"/>
	<SubTexture name="Character0004" x="5590" y="2831" width="859" height="859" frameX="-169" frameY="-82" frameWidth="1215" frameHeight="1097"/>
	<SubTexture name="Character0005" x="3" y="3662" width="800" height="800" frameX="-200" frameY="-129" frameWidth="1215" frameHeight="1097"/>
	<SubTexture name="Character0006" x="4666" y="2833" width="839" height="839" frameX="-162" frameY="-62" frameWidth="1215" frameHeight="1097"/>
	<SubTexture name="Character0007" x="3" y="3" width="1042" height="1001" frameX="0" frameY="-96" frameWidth="1215" frameHeight="1097"/>
	<SubTexture name="Character0008" x="6922" y="3" width="956" height="956" frameX="-62" frameY="-64" frameWidth="1215" frameHeight="1097"/>
	<SubTexture name="Character0009" x="1048" y="949" width="931" height="931" frameX="-185" frameY="-5" frameWidth="1215" frameHeight="1097"/>
	<SubTexture name="Character0010" x="5960" y="3" width="959" height="957" frameX="-256" frameY="0" frameWidth="1215" frameHeight="1097"/>
	<SubTexture name="Character0011" x="6652" y="2830" width="875" height="874" frameX="-141" frameY="-80" frameWidth="1215" frameHeight="1097"/>
	<SubTexture name="Character0012" x="909" y="2817" width="876" height="876" frameX="-151" frameY="-47" frameWidth="1215" frameHeight="1097"/>
	<SubTexture name="Character0013" x="1788" y="2844" width="825" height="826" frameX="-157" frameY="-106" frameWidth="1215" frameHeight="1097"/>
	<SubTexture name="Character0014" x="1048" y="3" width="1017" height="943" frameX="-164" frameY="-120" frameWidth="1215" frameHeight="1097"/>
	<SubTexture name="Character0015" x="3421" y="3673" width="658" height="861" frameX="-292" frameY="-85" frameWidth="1215" frameHeight="1097"/>
	<SubTexture name="Character0016" x="7828" y="1896" width="338" height="272" frameX="-447" frameY="-388" frameWidth="1215" frameHeight="1097"/>
	<SubTexture name="Character0017" x="4789" y="3675" width="673" height="697" frameX="-245" frameY="-160" frameWidth="1215" frameHeight="1097"/>
	<SubTexture name="Character0018" x="1788" y="3673" width="734" height="792" frameX="-222" frameY="-155" frameWidth="1215" frameHeight="1097"/>
	<SubTexture name="Character0019" x="3" y="1941" width="903" height="903" frameX="-162" frameY="-102" frameWidth="1215" frameHeight="1097"/>
	<SubTexture name="Character0020" x="6922" y="962" width="931" height="931" frameX="-185" frameY="-5" frameWidth="1215" frameHeight="1097"/>
	<SubTexture name="Character0021" x="5960" y="963" width="931" height="931" frameX="-185" frameY="-5" frameWidth="1215" frameHeight="1097"/>
	<SubTexture name="Character0022" x="1982" y="976" width="931" height="931" frameX="-185" frameY="-5" frameWidth="1215" frameHeight="1097"/>
	<SubTexture name="Character0023" x="2916" y="976" width="931" height="931" frameX="-185" frameY="-5" frameWidth="1215" frameHeight="1097"/>
	<SubTexture name="Character0024" x="4082" y="3675" width="704" height="775" frameX="-208" frameY="-102" frameWidth="1215" frameHeight="1097"/>
	<SubTexture name="Character0025" x="3739" y="1910" width="924" height="924" frameX="-183" frameY="-12" frameWidth="1215" frameHeight="1097"/>
	<SubTexture name="Character0026" x="2616" y="3659" width="802" height="802" frameX="-228" frameY="-107" frameWidth="1215" frameHeight="1097"/>
	<SubTexture name="Character0027" x="5465" y="3693" width="679" height="679" frameX="-278" frameY="-156" frameWidth="1215" frameHeight="1097"/>
	<SubTexture name="Character0028" x="3850" y="976" width="931" height="931" frameX="-185" frameY="-5" frameWidth="1215" frameHeight="1097"/>
	<SubTexture name="Character0029" x="4784" y="976" width="931" height="931" frameX="-185" frameY="-5" frameWidth="1215" frameHeight="1097"/>
	<SubTexture name="Character0030" x="3" y="1007" width="931" height="931" frameX="-185" frameY="-5" frameWidth="1215" frameHeight="1097"/>
	<SubTexture name="Character0031" x="937" y="1883" width="931" height="931" frameX="-185" frameY="-5" frameWidth="1215" frameHeight="1097"/>
	<SubTexture name="Character0032" x="6894" y="1896" width="931" height="931" frameX="-185" frameY="-5" frameWidth="1215" frameHeight="1097"/>
	<SubTexture name="Character0033" x="5718" y="1897" width="931" height="931" frameX="-185" frameY="-5" frameWidth="1215" frameHeight="1097"/>
	<SubTexture name="Character0034" x="806" y="3696" width="716" height="588" frameX="-263" frameY="-171" frameWidth="1215" frameHeight="1097"/>
	<SubTexture name="Character0035" x="1871" y="1910" width="931" height="931" frameX="-185" frameY="-5" frameWidth="1215" frameHeight="1097"/>
	<SubTexture name="Character0036" x="2805" y="1910" width="931" height="931" frameX="-185" frameY="-5" frameWidth="1215" frameHeight="1097"/>
	<SubTexture name="Character0037" x="7530" y="2830" width="598" height="598" frameX="-441" frameY="-242" frameWidth="1215" frameHeight="1097"/>
	<SubTexture name="Character0038" x="2068" y="3" width="970" height="970" frameX="-185" frameY="-5" frameWidth="1215" frameHeight="1097"/>
	<SubTexture name="Character0039" x="3041" y="3" width="970" height="970" frameX="-185" frameY="-5" frameWidth="1215" frameHeight="1097"/>
	<SubTexture name="Character0040" x="4014" y="3" width="970" height="970" frameX="-185" frameY="-5" frameWidth="1215" frameHeight="1097"/>
	<SubTexture name="Character0041" x="4987" y="3" width="970" height="970" frameX="-185" frameY="-5" frameWidth="1215" frameHeight="1097"/>
	<SubTexture name="Character0042" x="3" y="3" width="0" height="0" frameX="-192" frameY="-128" frameWidth="1215" frameHeight="1097"/>
</TextureAtlas>
