{
	"song": {
		"player1": "bf",
		"player2": "crewmate",
		"notes": [
			{
				"typeOfSection": 0,
				"lengthInSteps": 16,
				"sectionNotes": [
					[
						0,
						-1,
						"HUD Fade",
						"1",
						""
					]
				],
				"altAnim": false,
				"mustHitSection": false,
				"bpm": 150
			},
			{
				"typeOfSection": 0,
				"lengthInSteps": 16,
				"sectionNotes": [],
				"altAnim": false,
				"mustHitSection": true,
				"bpm": 150
			},
			{
				"typeOfSection": 0,
				"lengthInSteps": 16,
				"sectionNotes": [],
				"altAnim": false,
				"mustHitSection": false,
				"bpm": 150
			},
			{
				"typeOfSection": 0,
				"lengthInSteps": 16,
				"sectionNotes": [],
				"altAnim": false,
				"mustHitSection": true,
				"bpm": 150
			},
			{
				"typeOfSection": 0,
				"lengthInSteps": 16,
				"sectionNotes": [],
				"altAnim": false,
				"mustHitSection": false,
				"bpm": 150
			},
			{
				"typeOfSection": 0,
				"lengthInSteps": 16,
				"sectionNotes": [],
				"altAnim": false,
				"mustHitSection": true,
				"bpm": 150
			},
			{
				"typeOfSection": 0,
				"lengthInSteps": 16,
				"sectionNotes": [],
				"altAnim": false,
				"mustHitSection": false,
				"bpm": 150
			},
			{
				"typeOfSection": 0,
				"lengthInSteps": 16,
				"sectionNotes": [
					[
						11200,
						-1,
						"Add Camera Zoom",
						"",
						""
					],
					[
						11600,
						-1,
						"Add Camera Zoom",
						"",
						""
					],
					[
						12000,
						-1,
						"Add Camera Zoom",
						"",
						""
					],
					[
						12400,
						-1,
						"Add Camera Zoom",
						"",
						""
					],
					[
						11204.1666666667,
						-1,
						"Play Animation",
						"bopL",
						"Dad"
					],
					[
						11604.1666666667,
						-1,
						"Play Animation",
						"bopR",
						"Dad"
					],
					[
						12004.1666666667,
						-1,
						"Play Animation",
						"bopL",
						"Dad"
					],
					[
						12404.1666666667,
						-1,
						"Play Animation",
						"bopR",
						"Dad"
					],
					[
						12700,
						-1,
						"HUD Fade",
						"0",
						""
					]
				],
				"altAnim": false,
				"mustHitSection": false,
				"bpm": 150
			},
			{
				"typeOfSection": 0,
				"lengthInSteps": 16,
				"sectionNotes": [
					[
						12800,
						3,
						0
					],
					[
						12900,
						2,
						0
					],
					[
						13000,
						0,
						100
					],
					[
						13200,
						2,
						0
					],
					[
						13400,
						3,
						0
					],
					[
						13600,
						0,
						100
					],
					[
						13800,
						1,
						0
					],
					[
						14000,
						2,
						0
					],
					[
						14200,
						0,
						100
					],
					[
						13600,
						2,
						0
					]
				],
				"altAnim": false,
				"mustHitSection": false,
				"bpm": 150
			},
			{
				"typeOfSection": 0,
				"lengthInSteps": 16,
				"sectionNotes": [
					[
						14400,
						1,
						0
					],
					[
						14500,
						2,
						0
					],
					[
						14600,
						1,
						0
					],
					[
						14800,
						0,
						0
					],
					[
						15000,
						2,
						0
					],
					[
						15100,
						3,
						0
					],
					[
						15200,
						1,
						0
					],
					[
						15400,
						0,
						0
					],
					[
						15600,
						3,
						0
					],
					[
						15800,
						0,
						0
					]
				],
				"altAnim": false,
				"mustHitSection": false,
				"bpm": 150
			},
			{
				"typeOfSection": 0,
				"lengthInSteps": 16,
				"sectionNotes": [
					[
						16000,
						1,
						0
					],
					[
						16200,
						2,
						0
					],
					[
						16300,
						3,
						100
					],
					[
						16600,
						1,
						0
					],
					[
						16800,
						2,
						0
					],
					[
						17000,
						1,
						0
					],
					[
						17200,
						0,
						0
					],
					[
						17400,
						1,
						0
					]
				],
				"altAnim": false,
				"mustHitSection": false,
				"bpm": 150
			},
			{
				"typeOfSection": 0,
				"lengthInSteps": 16,
				"sectionNotes": [
					[
						17600,
						2,
						0
					],
					[
						17700,
						0,
						0
					],
					[
						17800,
						3,
						0
					],
					[
						18000,
						1,
						0
					],
					[
						18200,
						2,
						0
					],
					[
						18400,
						3,
						0
					],
					[
						18600,
						2,
						0
					],
					[
						18800,
						1,
						0
					],
					[
						19000,
						0,
						0
					]
				],
				"altAnim": false,
				"mustHitSection": false,
				"bpm": 150
			},
			{
				"typeOfSection": 0,
				"lengthInSteps": 16,
				"sectionNotes": [
					[
						19200,
						3,
						0
					],
					[
						19200,
						7,
						600
					],
					[
						19300,
						1,
						0
					],
					[
						19400,
						0,
						200
					],
					[
						19400,
						2,
						100
					],
					[
						19600,
						3,
						0
					],
					[
						19800,
						2,
						0
					],
					[
						20000,
						0,
						0
					],
					[
						20000,
						1,
						100
					],
					[
						20200,
						2,
						0
					],
					[
						20400,
						3,
						0
					],
					[
						20600,
						2,
						0
					]
				],
				"altAnim": false,
				"mustHitSection": true,
				"bpm": 150
			},
			{
				"typeOfSection": 0,
				"lengthInSteps": 16,
				"sectionNotes": [
					[
						20800,
						1,
						0
					],
					[
						20900,
						3,
						0
					],
					[
						21000,
						0,
						0
					],
					[
						21200,
						2,
						0
					],
					[
						21400,
						3,
						0
					],
					[
						21500,
						1,
						0
					],
					[
						21600,
						2,
						0
					],
					[
						21800,
						0,
						0
					],
					[
						21800,
						1,
						0
					],
					[
						22000,
						2,
						0
					],
					[
						22200,
						1,
						0
					]
				],
				"altAnim": false,
				"mustHitSection": true,
				"bpm": 150
			},
			{
				"typeOfSection": 0,
				"lengthInSteps": 16,
				"sectionNotes": [
					[
						22400,
						3,
						0
					],
					[
						22600,
						0,
						0
					],
					[
						22700,
						2,
						200
					],
					[
						22700,
						3,
						0
					],
					[
						23000,
						1,
						0
					],
					[
						23200,
						3,
						0
					],
					[
						23400,
						1,
						0
					],
					[
						23600,
						2,
						0
					],
					[
						23800,
						1,
						0
					],
					[
						23800,
						0,
						0
					]
				],
				"altAnim": false,
				"mustHitSection": true,
				"bpm": 150
			},
			{
				"typeOfSection": 0,
				"lengthInSteps": 16,
				"sectionNotes": [
					[
						24000,
						4,
						300
					],
					[
						24000,
						2,
						300
					],
					[
						24400,
						6,
						300
					],
					[
						24400,
						3,
						300
					],
					[
						24800,
						7,
						300
					],
					[
						24800,
						2,
						300
					],
					[
						25200,
						6,
						300
					],
					[
						25200,
						0,
						0
					],
					[
						25400,
						1,
						0
					],
					[
						24000,
						-1,
						"Add Camera Zoom",
						"",
						""
					],
					[
						24400,
						-1,
						"Add Camera Zoom",
						"",
						""
					],
					[
						24800,
						-1,
						"Add Camera Zoom",
						"",
						""
					],
					[
						25200,
						-1,
						"Add Camera Zoom",
						"",
						""
					]
				],
				"altAnim": false,
				"mustHitSection": true,
				"bpm": 150
			},
			{
				"typeOfSection": 0,
				"lengthInSteps": 16,
				"sectionNotes": [
					[
						25600,
						7,
						900
					],
					[
						25600,
						1,
						0
					],
					[
						25700,
						0,
						0
					],
					[
						25800,
						3,
						0
					],
					[
						26000,
						2,
						0
					],
					[
						26200,
						1,
						0
					],
					[
						26400,
						2,
						0
					],
					[
						26600,
						6,
						0
					],
					[
						26600,
						3,
						0
					],
					[
						26700,
						1,
						0
					],
					[
						26800,
						7,
						0
					],
					[
						26800,
						0,
						0
					],
					[
						27000,
						1,
						0
					],
					[
						27000,
						5,
						0
					]
				],
				"altAnim": false,
				"mustHitSection": false,
				"bpm": 150
			},
			{
				"typeOfSection": 0,
				"lengthInSteps": 16,
				"sectionNotes": [
					[
						27200,
						4,
						700
					],
					[
						27200,
						3,
						0
					],
					[
						27300,
						2,
						0
					],
					[
						27400,
						0,
						0
					],
					[
						27600,
						3,
						0
					],
					[
						27800,
						3,
						0
					],
					[
						28000,
						1,
						0
					],
					[
						28000,
						7,
						0
					],
					[
						28200,
						0,
						0
					],
					[
						28200,
						4,
						0
					],
					[
						28400,
						2,
						0
					],
					[
						28400,
						7,
						0
					],
					[
						28600,
						3,
						0
					],
					[
						28600,
						4,
						0
					],
					[
						27450,
						1,
						0
					],
					[
						27500,
						2,
						0
					],
					[
						27550,
						0,
						0
					],
					[
						27850,
						1,
						0
					],
					[
						27900,
						2,
						0
					]
				],
				"altAnim": false,
				"mustHitSection": false,
				"bpm": 150
			},
			{
				"typeOfSection": 0,
				"lengthInSteps": 16,
				"sectionNotes": [
					[
						28800,
						1,
						0
					],
					[
						28800,
						7,
						600
					],
					[
						28800,
						6,
						1100
					],
					[
						29000,
						2,
						0
					],
					[
						29100,
						0,
						200
					],
					[
						29100,
						1,
						0
					],
					[
						29400,
						1,
						0
					],
					[
						30000,
						2,
						0
					],
					[
						30000,
						4,
						300
					],
					[
						30200,
						1,
						0
					],
					[
						29950,
						3,
						0
					],
					[
						29850,
						0,
						0
					],
					[
						29900,
						1,
						0
					],
					[
						29800,
						2,
						0
					],
					[
						29600,
						3,
						0
					]
				],
				"altAnim": false,
				"mustHitSection": false,
				"bpm": 150
			},
			{
				"typeOfSection": 0,
				"lengthInSteps": 16,
				"sectionNotes": [
					[
						30400,
						6,
						0
					],
					[
						30400,
						2,
						0
					],
					[
						30500,
						3,
						0
					],
					[
						30600,
						7,
						0
					],
					[
						30600,
						2,
						0
					],
					[
						30700,
						0,
						0
					],
					[
						30750,
						1,
						0
					],
					[
						30800,
						5,
						0
					],
					[
						30800,
						3,
						0
					],
					[
						31000,
						6,
						0
					],
					[
						31000,
						2,
						0
					],
					[
						31100,
						0,
						0
					],
					[
						31200,
						4,
						0
					],
					[
						31200,
						2,
						0
					],
					[
						31400,
						7,
						0
					],
					[
						31400,
						3,
						0
					],
					[
						31600,
						6,
						0
					],
					[
						31600,
						1,
						200
					],
					[
						31700,
						5,
						0
					],
					[
						31800,
						7,
						0
					],
					[
						31900,
						4,
						0
					]
				],
				"altAnim": false,
				"mustHitSection": false,
				"bpm": 150
			},
			{
				"typeOfSection": 0,
				"lengthInSteps": 16,
				"sectionNotes": [
					[
						32000,
						1,
						0
					],
					[
						32000,
						7,
						900
					],
					[
						32100,
						0,
						0
					],
					[
						32200,
						3,
						0
					],
					[
						32400,
						2,
						0
					],
					[
						32600,
						1,
						0
					],
					[
						32800,
						2,
						0
					],
					[
						33000,
						3,
						0
					],
					[
						33100,
						1,
						0
					],
					[
						33200,
						0,
						0
					],
					[
						33400,
						2,
						0
					]
				],
				"altAnim": false,
				"mustHitSection": true,
				"bpm": 150
			},
			{
				"typeOfSection": 0,
				"lengthInSteps": 16,
				"sectionNotes": [
					[
						33600,
						1,
						0
					],
					[
						33700,
						0,
						0
					],
					[
						33800,
						2,
						0
					],
					[
						34200,
						1,
						0
					],
					[
						34250,
						2,
						0
					],
					[
						34300,
						3,
						0
					],
					[
						34400,
						0,
						0
					],
					[
						34600,
						1,
						0
					],
					[
						34800,
						2,
						0
					],
					[
						35000,
						1,
						0
					],
					[
						33650,
						2,
						0
					],
					[
						33750,
						1,
						0
					],
					[
						33850,
						3,
						0
					],
					[
						33900,
						1,
						0
					],
					[
						33950,
						0,
						0
					],
					[
						34000,
						2,
						0
					]
				],
				"altAnim": false,
				"mustHitSection": true,
				"bpm": 150
			},
			{
				"typeOfSection": 0,
				"lengthInSteps": 16,
				"sectionNotes": [
					[
						35200,
						3,
						0
					],
					[
						35400,
						0,
						0
					],
					[
						35500,
						1,
						200
					],
					[
						35800,
						2,
						0
					],
					[
						36000,
						3,
						100
					],
					[
						36000,
						1,
						0
					],
					[
						36200,
						2,
						0
					],
					[
						36300,
						1,
						0
					],
					[
						36350,
						0,
						0
					],
					[
						36400,
						3,
						0
					],
					[
						36600,
						1,
						0
					],
					[
						35500,
						3,
						0
					]
				],
				"altAnim": false,
				"mustHitSection": true,
				"bpm": 150
			},
			{
				"typeOfSection": 0,
				"lengthInSteps": 16,
				"sectionNotes": [
					[
						36800,
						6,
						0
					],
					[
						36800,
						2,
						0
					],
					[
						36900,
						0,
						0
					],
					[
						37000,
						2,
						0
					],
					[
						37100,
						0,
						0
					],
					[
						37150,
						1,
						0
					],
					[
						37200,
						5,
						0
					],
					[
						37200,
						3,
						0
					],
					[
						37400,
						2,
						0
					],
					[
						37500,
						1,
						0
					],
					[
						37600,
						4,
						0
					],
					[
						37600,
						0,
						0
					],
					[
						37800,
						2,
						0
					],
					[
						38000,
						6,
						0
					],
					[
						38000,
						3,
						300
					],
					[
						38000,
						1,
						200
					],
					[
						38200,
						5,
						0
					],
					[
						36800,
						-1,
						"Add Camera Zoom",
						"",
						""
					],
					[
						37200,
						-1,
						"Add Camera Zoom",
						"",
						""
					],
					[
						37600,
						-1,
						"Add Camera Zoom",
						"",
						""
					],
					[
						38000,
						-1,
						"Add Camera Zoom",
						"",
						""
					]
				],
				"altAnim": false,
				"mustHitSection": true,
				"bpm": 150
			},
			{
				"typeOfSection": 0,
				"lengthInSteps": 16,
				"sectionNotes": [
					[
						38400,
						3,
						0
					],
					[
						38400,
						4,
						900
					],
					[
						38600,
						2,
						0
					],
					[
						38700,
						0,
						0
					],
					[
						38900,
						2,
						0
					],
					[
						39000,
						1,
						0
					],
					[
						39100,
						3,
						0
					],
					[
						39200,
						2,
						0
					],
					[
						39300,
						1,
						0
					],
					[
						39400,
						0,
						0
					],
					[
						39400,
						6,
						0
					],
					[
						39600,
						2,
						0
					],
					[
						39600,
						7,
						0
					],
					[
						39800,
						3,
						0
					],
					[
						39800,
						4,
						0
					]
				],
				"altAnim": false,
				"mustHitSection": false,
				"bpm": 150
			},
			{
				"typeOfSection": 0,
				"lengthInSteps": 16,
				"sectionNotes": [
					[
						40000,
						2,
						0
					],
					[
						40000,
						7,
						700
					],
					[
						40200,
						0,
						0
					],
					[
						40300,
						1,
						0
					],
					[
						40400,
						3,
						0
					],
					[
						40600,
						2,
						0
					],
					[
						40800,
						1,
						0
					],
					[
						40800,
						6,
						0
					],
					[
						41000,
						3,
						0
					],
					[
						41000,
						4,
						0
					],
					[
						41200,
						0,
						0
					],
					[
						41200,
						7,
						0
					],
					[
						41400,
						1,
						0
					],
					[
						41400,
						5,
						0
					]
				],
				"altAnim": false,
				"mustHitSection": false,
				"bpm": 150
			},
			{
				"typeOfSection": 0,
				"lengthInSteps": 16,
				"sectionNotes": [
					[
						41600,
						2,
						0
					],
					[
						41600,
						6,
						1100
					],
					[
						41600,
						4,
						800
					],
					[
						41800,
						3,
						0
					],
					[
						41900,
						1,
						0
					],
					[
						42000,
						3,
						100
					],
					[
						42200,
						2,
						0
					],
					[
						42400,
						1,
						0
					],
					[
						42600,
						0,
						0
					],
					[
						42800,
						2,
						0
					],
					[
						42800,
						7,
						300
					],
					[
						43000,
						1,
						0
					]
				],
				"altAnim": false,
				"mustHitSection": false,
				"bpm": 150
			},
			{
				"typeOfSection": 0,
				"lengthInSteps": 16,
				"sectionNotes": [
					[
						43200,
						1,
						0
					],
					[
						43200,
						6,
						0
					],
					[
						43400,
						3,
						0
					],
					[
						43400,
						5,
						0
					],
					[
						43600,
						2,
						0
					],
					[
						43600,
						4,
						0
					],
					[
						43800,
						0,
						0
					],
					[
						43800,
						7,
						0
					],
					[
						44000,
						2,
						0
					],
					[
						44000,
						6,
						0
					],
					[
						44100,
						1,
						0
					],
					[
						44200,
						5,
						100
					],
					[
						44300,
						3,
						0
					],
					[
						44400,
						1,
						100
					],
					[
						44400,
						7,
						0
					],
					[
						44500,
						5,
						0
					],
					[
						44600,
						0,
						0
					],
					[
						44600,
						4,
						0
					],
					[
						44700,
						6,
						0
					],
					[
						44200,
						4,
						0
					]
				],
				"altAnim": false,
				"mustHitSection": false,
				"bpm": 150
			},
			{
				"typeOfSection": 0,
				"lengthInSteps": 16,
				"sectionNotes": [
					[
						44800,
						7,
						300
					],
					[
						44800,
						3,
						0
					],
					[
						45000,
						0,
						0
					],
					[
						45100,
						3,
						0
					],
					[
						45300,
						0,
						0
					],
					[
						45400,
						3,
						0
					],
					[
						45500,
						0,
						0
					],
					[
						45800,
						3,
						0
					],
					[
						46000,
						1,
						0
					],
					[
						46200,
						2,
						0
					],
					[
						45600,
						1,
						0
					],
					[
						45700,
						2,
						0
					]
				],
				"altAnim": false,
				"mustHitSection": true,
				"bpm": 150
			},
			{
				"typeOfSection": 0,
				"lengthInSteps": 16,
				"sectionNotes": [
					[
						46400,
						0,
						0
					],
					[
						46600,
						1,
						0
					],
					[
						46700,
						0,
						0
					],
					[
						46800,
						1,
						0
					],
					[
						47000,
						0,
						0
					],
					[
						47200,
						2,
						0
					],
					[
						47400,
						3,
						0
					],
					[
						47600,
						0,
						0
					],
					[
						47800,
						2,
						0
					]
				],
				"altAnim": false,
				"mustHitSection": true,
				"bpm": 150
			},
			{
				"typeOfSection": 0,
				"lengthInSteps": 16,
				"sectionNotes": [
					[
						48000,
						3,
						0
					],
					[
						48200,
						2,
						0
					],
					[
						48300,
						3,
						0
					],
					[
						48400,
						2,
						0
					],
					[
						48600,
						3,
						0
					],
					[
						48800,
						1,
						0
					],
					[
						49000,
						2,
						0
					],
					[
						49200,
						0,
						0
					],
					[
						49400,
						3,
						0
					],
					[
						48900,
						3,
						0
					]
				],
				"altAnim": false,
				"mustHitSection": true,
				"bpm": 150
			},
			{
				"typeOfSection": 0,
				"lengthInSteps": 16,
				"sectionNotes": [
					[
						49600,
						0,
						0
					],
					[
						49800,
						4,
						0
					],
					[
						49800,
						2,
						0
					],
					[
						50000,
						6,
						0
					],
					[
						50000,
						3,
						0
					],
					[
						50200,
						5,
						0
					],
					[
						50200,
						2,
						0
					],
					[
						50400,
						7,
						300
					],
					[
						50400,
						0,
						100
					],
					[
						50500,
						2,
						0
					],
					[
						50700,
						1,
						100
					],
					[
						50800,
						6,
						0
					],
					[
						51000,
						3,
						0
					],
					[
						51100,
						1,
						0
					],
					[
						49600,
						-1,
						"Add Camera Zoom",
						"",
						""
					],
					[
						50000,
						-1,
						"Add Camera Zoom",
						"",
						""
					],
					[
						50400,
						-1,
						"Add Camera Zoom",
						"",
						""
					],
					[
						50800,
						-1,
						"Add Camera Zoom",
						"",
						""
					],
					[
						50400,
						1,
						0
					],
					[
						50700,
						3,
						0
					]
				],
				"altAnim": false,
				"mustHitSection": true,
				"bpm": 150
			},
			{
				"typeOfSection": 0,
				"lengthInSteps": 16,
				"sectionNotes": [
					[
						51200,
						0,
						0
					],
					[
						51200,
						4,
						600
					],
					[
						51300,
						3,
						0
					],
					[
						51400,
						0,
						0
					],
					[
						51600,
						2,
						0
					],
					[
						51800,
						1,
						0
					],
					[
						52000,
						3,
						0
					],
					[
						52000,
						7,
						300
					],
					[
						52200,
						1,
						0
					],
					[
						52400,
						0,
						0
					],
					[
						52400,
						4,
						300
					],
					[
						52600,
						2,
						0
					]
				],
				"altAnim": false,
				"mustHitSection": false,
				"bpm": 150
			},
			{
				"typeOfSection": 0,
				"lengthInSteps": 16,
				"sectionNotes": [
					[
						52800,
						1,
						0
					],
					[
						53000,
						3,
						0
					],
					[
						53200,
						2,
						0
					],
					[
						53200,
						5,
						700
					],
					[
						53400,
						0,
						0
					],
					[
						53500,
						0,
						0
					],
					[
						53600,
						3,
						0
					],
					[
						53800,
						1,
						0
					],
					[
						54000,
						2,
						0
					],
					[
						54000,
						7,
						0
					],
					[
						54200,
						1,
						0
					],
					[
						54200,
						6,
						0
					],
					[
						52800,
						7,
						300
					],
					[
						53000,
						6,
						200
					],
					[
						52900,
						2,
						0
					]
				],
				"altAnim": false,
				"mustHitSection": false,
				"bpm": 150
			},
			{
				"typeOfSection": 0,
				"lengthInSteps": 16,
				"sectionNotes": [
					[
						54400,
						0,
						0
					],
					[
						54400,
						4,
						300
					],
					[
						54600,
						3,
						0
					],
					[
						54700,
						2,
						100
					],
					[
						54800,
						7,
						1100
					],
					[
						54800,
						6,
						700
					],
					[
						55000,
						1,
						0
					],
					[
						55200,
						0,
						0
					],
					[
						55400,
						3,
						0
					],
					[
						55600,
						2,
						0
					],
					[
						55800,
						3,
						0
					]
				],
				"altAnim": false,
				"mustHitSection": false,
				"bpm": 150
			},
			{
				"typeOfSection": 0,
				"lengthInSteps": 16,
				"sectionNotes": [
					[
						56000,
						2,
						0
					],
					[
						56000,
						4,
						300
					],
					[
						56100,
						0,
						0
					],
					[
						56200,
						3,
						0
					],
					[
						56400,
						1,
						0
					],
					[
						56400,
						6,
						700
					],
					[
						56600,
						0,
						0
					],
					[
						56700,
						7,
						400
					],
					[
						56800,
						2,
						0
					],
					[
						57000,
						3,
						0
					],
					[
						57200,
						1,
						0
					],
					[
						57200,
						4,
						300
					],
					[
						57400,
						0,
						0
					],
					[
						56800,
						5,
						200
					]
				],
				"altAnim": false,
				"mustHitSection": false,
				"bpm": 150
			},
			{
				"typeOfSection": 0,
				"lengthInSteps": 16,
				"sectionNotes": [
					[
						57600,
						1,
						0
					],
					[
						57600,
						7,
						900
					],
					[
						57800,
						3,
						0
					],
					[
						58000,
						2,
						0
					],
					[
						58200,
						1,
						0
					],
					[
						58400,
						2,
						0
					],
					[
						58600,
						3,
						0
					],
					[
						58700,
						1,
						0
					],
					[
						58800,
						0,
						0
					],
					[
						59000,
						2,
						0
					],
					[
						57700,
						1,
						0
					]
				],
				"altAnim": false,
				"mustHitSection": true,
				"bpm": 150
			},
			{
				"typeOfSection": 0,
				"lengthInSteps": 16,
				"sectionNotes": [
					[
						59300,
						0,
						0
					],
					[
						59400,
						2,
						0
					],
					[
						59800,
						1,
						0
					],
					[
						59850,
						2,
						0
					],
					[
						59900,
						3,
						0
					],
					[
						60000,
						0,
						0
					],
					[
						60200,
						1,
						0
					],
					[
						60400,
						2,
						0
					],
					[
						60600,
						1,
						100
					],
					[
						60600,
						0,
						0
					],
					[
						59250,
						2,
						0
					],
					[
						59350,
						1,
						0
					],
					[
						59450,
						3,
						0
					],
					[
						59200,
						3,
						0
					],
					[
						59500,
						1,
						0
					],
					[
						59550,
						0,
						0
					],
					[
						59600,
						2,
						0
					]
				],
				"altAnim": false,
				"mustHitSection": true,
				"bpm": 150
			},
			{
				"typeOfSection": 0,
				"lengthInSteps": 16,
				"sectionNotes": [
					[
						60800,
						3,
						0
					],
					[
						61000,
						0,
						0
					],
					[
						61100,
						1,
						0
					],
					[
						61400,
						2,
						0
					],
					[
						61600,
						3,
						0
					],
					[
						61600,
						1,
						0
					],
					[
						61800,
						2,
						0
					],
					[
						61900,
						1,
						0
					],
					[
						61950,
						0,
						0
					],
					[
						62200,
						1,
						0
					],
					[
						61100,
						3,
						200
					],
					[
						61850,
						3,
						0
					],
					[
						62000,
						2,
						0
					]
				],
				"altAnim": false,
				"mustHitSection": true,
				"bpm": 150
			},
			{
				"typeOfSection": 0,
				"lengthInSteps": 16,
				"sectionNotes": [
					[
						62400,
						2,
						0
					],
					[
						62500,
						0,
						0
					],
					[
						62600,
						2,
						0
					],
					[
						62700,
						0,
						0
					],
					[
						62750,
						1,
						0
					],
					[
						62800,
						3,
						0
					],
					[
						63000,
						2,
						0
					],
					[
						63100,
						1,
						0
					],
					[
						63200,
						0,
						0
					],
					[
						63400,
						2,
						0
					],
					[
						63600,
						3,
						300
					],
					[
						63600,
						1,
						200
					],
					[
						62400,
						-1,
						"Add Camera Zoom",
						"",
						""
					],
					[
						62800,
						-1,
						"Add Camera Zoom",
						"",
						""
					],
					[
						63200,
						-1,
						"Add Camera Zoom",
						"",
						""
					],
					[
						63600,
						-1,
						"Add Camera Zoom",
						"",
						""
					]
				],
				"altAnim": false,
				"mustHitSection": true,
				"bpm": 150
			},
			{
				"typeOfSection": 0,
				"lengthInSteps": 16,
				"sectionNotes": [
					[
						64000,
						6,
						300
					],
					[
						64400,
						1,
						0
					],
					[
						64600,
						2,
						0
					],
					[
						64800,
						3,
						0
					],
					[
						64900,
						2,
						0
					],
					[
						65000,
						1,
						0
					],
					[
						65200,
						0,
						0
					],
					[
						65400,
						1,
						0
					]
				],
				"altAnim": false,
				"mustHitSection": false,
				"bpm": 150
			},
			{
				"typeOfSection": 0,
				"lengthInSteps": 16,
				"sectionNotes": [
					[
						65600,
						1,
						0
					],
					[
						66000,
						2,
						0
					],
					[
						66200,
						3,
						0
					],
					[
						66300,
						0,
						0
					],
					[
						66500,
						2,
						0
					],
					[
						66600,
						3,
						0
					],
					[
						66700,
						1,
						0
					],
					[
						66800,
						0,
						0
					],
					[
						67000,
						1,
						0
					],
					[
						67000,
						7,
						0
					],
					[
						65600,
						3,
						0
					]
				],
				"altAnim": false,
				"mustHitSection": false,
				"bpm": 150
			},
			{
				"typeOfSection": 0,
				"lengthInSteps": 16,
				"sectionNotes": [
					[
						67200,
						6,
						300
					],
					[
						67200,
						2,
						0
					],
					[
						67300,
						3,
						0
					],
					[
						67400,
						2,
						0
					],
					[
						67600,
						1,
						0
					],
					[
						67800,
						0,
						0
					],
					[
						68000,
						2,
						0
					],
					[
						68400,
						1,
						0
					],
					[
						68600,
						3,
						0
					]
				],
				"altAnim": false,
				"mustHitSection": false,
				"bpm": 150
			},
			{
				"typeOfSection": 0,
				"lengthInSteps": 16,
				"sectionNotes": [
					[
						68800,
						2,
						0
					],
					[
						68800,
						7,
						0
					],
					[
						69000,
						4,
						0
					],
					[
						69200,
						3,
						0
					],
					[
						69200,
						7,
						0
					],
					[
						69400,
						2,
						0
					],
					[
						69400,
						4,
						0
					],
					[
						69600,
						0,
						0
					],
					[
						69600,
						6,
						0
					],
					[
						69700,
						1,
						0
					],
					[
						69800,
						0,
						0
					],
					[
						69800,
						7,
						0
					],
					[
						70000,
						2,
						0
					],
					[
						70000,
						4,
						0
					],
					[
						70200,
						3,
						0
					],
					[
						70200,
						6,
						500
					]
				],
				"altAnim": false,
				"mustHitSection": false,
				"bpm": 150
			},
			{
				"typeOfSection": 0,
				"lengthInSteps": 16,
				"sectionNotes": [
					[
						70400,
						7,
						200
					],
					[
						70800,
						1,
						0
					],
					[
						71000,
						2,
						0
					],
					[
						71200,
						3,
						0
					],
					[
						71300,
						2,
						0
					],
					[
						71400,
						1,
						0
					],
					[
						71600,
						0,
						0
					],
					[
						71800,
						2,
						0
					]
				],
				"altAnim": false,
				"mustHitSection": true,
				"bpm": 150
			},
			{
				"typeOfSection": 0,
				"lengthInSteps": 16,
				"sectionNotes": [
					[
						72000,
						1,
						0
					],
					[
						72400,
						2,
						0
					],
					[
						72600,
						3,
						0
					],
					[
						72700,
						0,
						0
					],
					[
						73400,
						7,
						0
					],
					[
						72900,
						3,
						0
					],
					[
						73000,
						2,
						0
					],
					[
						73100,
						0,
						0
					],
					[
						73200,
						1,
						300
					],
					[
						73400,
						3,
						0
					],
					[
						73300,
						2,
						100
					]
				],
				"altAnim": false,
				"mustHitSection": true,
				"bpm": 150
			},
			{
				"typeOfSection": 0,
				"lengthInSteps": 16,
				"sectionNotes": [
					[
						73600,
						6,
						300
					],
					[
						73800,
						3,
						0
					],
					[
						74000,
						0,
						0
					],
					[
						74200,
						2,
						0
					],
					[
						74400,
						1,
						300
					],
					[
						74800,
						2,
						0
					],
					[
						75000,
						0,
						0
					],
					[
						73600,
						0,
						0
					],
					[
						73700,
						2,
						0
					]
				],
				"altAnim": false,
				"mustHitSection": true,
				"bpm": 150
			},
			{
				"typeOfSection": 0,
				"lengthInSteps": 16,
				"sectionNotes": [
					[
						75200,
						7,
						0
					],
					[
						75200,
						3,
						200
					],
					[
						75400,
						4,
						0
					],
					[
						75600,
						7,
						0
					],
					[
						75800,
						2,
						0
					],
					[
						75800,
						4,
						0
					],
					[
						76000,
						6,
						0
					],
					[
						76200,
						7,
						0
					],
					[
						76400,
						4,
						0
					],
					[
						76600,
						6,
						500
					],
					[
						75600,
						0,
						0
					],
					[
						76000,
						3,
						0
					],
					[
						76100,
						2,
						0
					],
					[
						76200,
						3,
						0
					],
					[
						76400,
						0,
						0
					],
					[
						76600,
						3,
						0
					]
				],
				"altAnim": false,
				"mustHitSection": true,
				"bpm": 150
			},
			{
				"typeOfSection": 0,
				"lengthInSteps": 16,
				"sectionNotes": [
					[
						76800,
						6,
						400
					],
					[
						77200,
						1,
						0
					],
					[
						77400,
						0,
						0
					],
					[
						77600,
						0,
						0
					],
					[
						77800,
						3,
						0
					],
					[
						78000,
						2,
						0
					]
				],
				"altAnim": false,
				"mustHitSection": false,
				"bpm": 150
			},
			{
				"typeOfSection": 0,
				"lengthInSteps": 16,
				"sectionNotes": [
					[
						78400,
						1,
						0
					],
					[
						78600,
						3,
						0
					],
					[
						78700,
						3,
						0
					],
					[
						78750,
						2,
						0
					],
					[
						79000,
						2,
						400
					],
					[
						79600,
						1,
						200
					],
					[
						78950,
						1,
						0
					],
					[
						78800,
						1,
						0
					],
					[
						78850,
						3,
						0
					],
					[
						78900,
						0,
						0
					]
				],
				"altAnim": false,
				"mustHitSection": false,
				"bpm": 150
			},
			{
				"typeOfSection": 0,
				"lengthInSteps": 16,
				"sectionNotes": [
					[
						80400,
						0,
						0
					],
					[
						80600,
						2,
						0
					],
					[
						81000,
						3,
						0
					]
				],
				"altAnim": false,
				"mustHitSection": false,
				"bpm": 150
			},
			{
				"typeOfSection": 0,
				"lengthInSteps": 16,
				"sectionNotes": [
					[
						81600,
						3,
						0
					],
					[
						81800,
						1,
						0
					],
					[
						82000,
						0,
						0
					],
					[
						82200,
						1,
						0
					],
					[
						82400,
						3,
						0
					],
					[
						82600,
						1,
						0
					],
					[
						82800,
						0,
						0
					],
					[
						83000,
						2,
						0
					]
				],
				"altAnim": false,
				"mustHitSection": false,
				"bpm": 150
			},
			{
				"typeOfSection": 0,
				"lengthInSteps": 16,
				"sectionNotes": [
					[
						84400,
						2,
						300
					],
					[
						83200,
						5,
						300
					],
					[
						83600,
						2,
						0
					],
					[
						83800,
						3,
						0
					],
					[
						84000,
						3,
						0
					],
					[
						84200,
						1,
						0
					]
				],
				"altAnim": false,
				"mustHitSection": true,
				"bpm": 150
			},
			{
				"typeOfSection": 0,
				"lengthInSteps": 16,
				"sectionNotes": [
					[
						84800,
						3,
						0
					],
					[
						85000,
						0,
						0
					],
					[
						85100,
						3,
						0
					],
					[
						85150,
						2,
						0
					],
					[
						85200,
						1,
						0
					],
					[
						85400,
						3,
						500
					],
					[
						86000,
						2,
						600
					],
					[
						85050,
						1,
						0
					],
					[
						85250,
						0,
						0
					],
					[
						85300,
						1,
						0
					],
					[
						85350,
						2,
						0
					]
				],
				"altAnim": false,
				"mustHitSection": true,
				"bpm": 150
			},
			{
				"typeOfSection": 0,
				"lengthInSteps": 16,
				"sectionNotes": [
					[
						87400,
						2,
						300
					],
					[
						86800,
						3,
						0
					],
					[
						87000,
						0,
						0
					]
				],
				"altAnim": false,
				"mustHitSection": true,
				"bpm": 150
			},
			{
				"typeOfSection": 0,
				"lengthInSteps": 16,
				"sectionNotes": [
					[
						88000,
						3,
						0
					],
					[
						88000,
						5,
						0
					],
					[
						88200,
						1,
						0
					],
					[
						88400,
						5,
						0
					],
					[
						88600,
						1,
						0
					],
					[
						88800,
						3,
						0
					],
					[
						88800,
						5,
						0
					],
					[
						89000,
						1,
						0
					],
					[
						89200,
						5,
						0
					],
					[
						89400,
						2,
						0
					],
					[
						88400,
						3,
						0
					],
					[
						89200,
						3,
						0
					],
					[
						88000,
						-1,
						"Add Camera Zoom",
						"",
						""
					],
					[
						88400,
						-1,
						"Add Camera Zoom",
						"",
						""
					],
					[
						88800,
						-1,
						"Add Camera Zoom",
						"",
						""
					],
					[
						89200,
						-1,
						"Add Camera Zoom",
						"",
						""
					]
				],
				"altAnim": false,
				"mustHitSection": true,
				"bpm": 150
			},
			{
				"typeOfSection": 0,
				"lengthInSteps": 16,
				"sectionNotes": [
					[
						89600,
						0,
						400
					],
					[
						89600,
						4,
						400
					],
					[
						89600,
						-1,
						"Toogus Sax",
						"",
						""
					]
				],
				"altAnim": false,
				"mustHitSection": false,
				"bpm": 150
			},
			{
				"typeOfSection": 0,
				"lengthInSteps": 16,
				"sectionNotes": [],
				"altAnim": false,
				"mustHitSection": false,
				"bpm": 150
			},
			{
				"typeOfSection": 0,
				"lengthInSteps": 16,
				"sectionNotes": [],
				"altAnim": false,
				"mustHitSection": false,
				"bpm": 150
			},
			{
				"typeOfSection": 0,
				"lengthInSteps": 16,
				"sectionNotes": [],
				"altAnim": false,
				"mustHitSection": false,
				"bpm": 150
			},
			{
				"typeOfSection": 0,
				"lengthInSteps": 16,
				"sectionNotes": [],
				"altAnim": false,
				"mustHitSection": true,
				"bpm": 150
			},
			{
				"typeOfSection": 0,
				"lengthInSteps": 16,
				"sectionNotes": [],
				"altAnim": false,
				"mustHitSection": true,
				"bpm": 150
			},
			{
				"typeOfSection": 0,
				"lengthInSteps": 16,
				"sectionNotes": [],
				"altAnim": false,
				"mustHitSection": true,
				"bpm": 150
			},
			{
				"typeOfSection": 0,
				"lengthInSteps": 16,
				"sectionNotes": [],
				"altAnim": false,
				"mustHitSection": true,
				"bpm": 150
			},
			{
				"typeOfSection": 0,
				"lengthInSteps": 16,
				"sectionNotes": [
					[
						102400,
						1,
						300
					],
					[
						102800,
						2,
						1100
					],
					[
						102600,
						0,
						200
					]
				],
				"altAnim": false,
				"mustHitSection": false,
				"bpm": 150
			},
			{
				"typeOfSection": 0,
				"lengthInSteps": 16,
				"sectionNotes": [
					[
						104000,
						3,
						400
					],
					[
						104400,
						0,
						1000
					]
				],
				"altAnim": false,
				"mustHitSection": false,
				"bpm": 150
			},
			{
				"typeOfSection": 0,
				"lengthInSteps": 16,
				"sectionNotes": [
					[
						105600,
						1,
						300
					],
					[
						106000,
						0,
						800
					]
				],
				"altAnim": false,
				"mustHitSection": false,
				"bpm": 150
			},
			{
				"typeOfSection": 0,
				"lengthInSteps": 16,
				"sectionNotes": [
					[
						107200,
						2,
						0
					],
					[
						107400,
						3,
						0
					],
					[
						108400,
						1,
						300
					],
					[
						107600,
						0,
						400
					]
				],
				"altAnim": false,
				"mustHitSection": false,
				"bpm": 150
			},
			{
				"typeOfSection": 0,
				"lengthInSteps": 16,
				"sectionNotes": [
					[
						108800,
						4,
						300
					],
					[
						108800,
						1,
						200
					],
					[
						109200,
						3,
						1100
					],
					[
						109200,
						2,
						1100
					],
					[
						108850,
						0,
						250
					]
				],
				"altAnim": false,
				"mustHitSection": true,
				"bpm": 150
			},
			{
				"typeOfSection": 0,
				"lengthInSteps": 16,
				"sectionNotes": [
					[
						110400,
						0,
						300
					],
					[
						110800,
						2,
						900
					],
					[
						111200,
						3,
						700
					]
				],
				"altAnim": false,
				"mustHitSection": true,
				"bpm": 150
			},
			{
				"typeOfSection": 0,
				"lengthInSteps": 16,
				"sectionNotes": [
					[
						112000,
						0,
						300
					],
					[
						112400,
						3,
						1000
					]
				],
				"altAnim": false,
				"mustHitSection": true,
				"bpm": 150
			},
			{
				"typeOfSection": 0,
				"lengthInSteps": 16,
				"sectionNotes": [
					[
						113800,
						7,
						0
					],
					[
						114000,
						1,
						200
					],
					[
						114000,
						4,
						0
					],
					[
						114200,
						6,
						0
					],
					[
						114400,
						5,
						0
					],
					[
						114800,
						7,
						300
					],
					[
						114850,
						6,
						0
					],
					[
						113600,
						1,
						0
					],
					[
						113800,
						2,
						0
					],
					[
						114000,
						3,
						700
					],
					[
						114800,
						2,
						300
					]
				],
				"altAnim": false,
				"mustHitSection": true,
				"bpm": 150
			},
			{
				"typeOfSection": 0,
				"lengthInSteps": 16,
				"sectionNotes": [
					[
						115200,
						1,
						0
					],
					[
						115400,
						0,
						0
					],
					[
						115500,
						0,
						0
					],
					[
						115600,
						2,
						0
					],
					[
						115700,
						3,
						0
					],
					[
						115800,
						1,
						0
					],
					[
						116000,
						0,
						0
					],
					[
						116200,
						2,
						0
					],
					[
						116400,
						3,
						0
					],
					[
						116600,
						1,
						0
					],
					[
						115200,
						4,
						300
					]
				],
				"altAnim": false,
				"mustHitSection": false,
				"bpm": 150
			},
			{
				"typeOfSection": 0,
				"lengthInSteps": 16,
				"sectionNotes": [
					[
						116800,
						2,
						0
					],
					[
						117000,
						1,
						0
					],
					[
						117100,
						0,
						0
					],
					[
						117200,
						3,
						0
					],
					[
						117400,
						2,
						0
					],
					[
						117600,
						3,
						0
					],
					[
						117800,
						0,
						0
					],
					[
						118000,
						1,
						0
					],
					[
						118200,
						2,
						0
					]
				],
				"altAnim": false,
				"mustHitSection": false,
				"bpm": 150
			},
			{
				"typeOfSection": 0,
				"lengthInSteps": 16,
				"sectionNotes": [
					[
						118400,
						3,
						0
					],
					[
						118600,
						0,
						0
					],
					[
						118700,
						2,
						0
					],
					[
						118800,
						3,
						0
					],
					[
						119000,
						2,
						0
					],
					[
						119200,
						1,
						0
					],
					[
						119300,
						0,
						0
					],
					[
						119400,
						1,
						0
					],
					[
						119800,
						3,
						0
					],
					[
						119900,
						2,
						0
					],
					[
						119600,
						2,
						0
					],
					[
						119600,
						0,
						0
					]
				],
				"altAnim": false,
				"mustHitSection": false,
				"bpm": 150
			},
			{
				"typeOfSection": 0,
				"lengthInSteps": 16,
				"sectionNotes": [
					[
						120000,
						0,
						0
					],
					[
						120100,
						3,
						0
					],
					[
						120200,
						2,
						0
					],
					[
						120300,
						1,
						0
					],
					[
						120400,
						2,
						0
					],
					[
						120600,
						3,
						0
					],
					[
						120800,
						3,
						0
					],
					[
						120950,
						2,
						0
					],
					[
						121100,
						1,
						0
					],
					[
						121200,
						3,
						0
					],
					[
						121350,
						2,
						0
					],
					[
						121500,
						1,
						0
					]
				],
				"altAnim": false,
				"mustHitSection": false,
				"bpm": 150
			},
			{
				"typeOfSection": 0,
				"lengthInSteps": 16,
				"sectionNotes": [
					[
						121600,
						4,
						100
					],
					[
						121800,
						1,
						0
					],
					[
						122000,
						0,
						0
					],
					[
						122400,
						2,
						0
					],
					[
						122100,
						1,
						0
					],
					[
						122200,
						3,
						0
					],
					[
						122600,
						0,
						0
					],
					[
						122800,
						3,
						0
					],
					[
						123000,
						0,
						0
					],
					[
						121600,
						0,
						100
					],
					[
						121900,
						1,
						0
					],
					[
						121833.333333333,
						3,
						0
					],
					[
						121866.666666667,
						2,
						0
					]
				],
				"altAnim": false,
				"mustHitSection": true,
				"bpm": 150
			},
			{
				"typeOfSection": 0,
				"lengthInSteps": 16,
				"sectionNotes": [
					[
						123200,
						2,
						0
					],
					[
						123200,
						3,
						0
					],
					[
						123400,
						0,
						0
					],
					[
						123500,
						1,
						0
					],
					[
						123800,
						3,
						0
					],
					[
						123600,
						2,
						0
					],
					[
						124000,
						2,
						0
					],
					[
						124200,
						1,
						0
					],
					[
						124400,
						2,
						0
					],
					[
						124600,
						0,
						0
					]
				],
				"altAnim": false,
				"mustHitSection": true,
				"bpm": 150
			},
			{
				"typeOfSection": 0,
				"lengthInSteps": 16,
				"sectionNotes": [
					[
						124800,
						2,
						0
					],
					[
						125000,
						1,
						0
					],
					[
						125100,
						2,
						0
					],
					[
						125200,
						3,
						0
					],
					[
						125400,
						2,
						0
					],
					[
						125400,
						0,
						0
					],
					[
						125600,
						3,
						0
					],
					[
						125700,
						2,
						0
					],
					[
						125800,
						3,
						0
					],
					[
						126000,
						0,
						0
					],
					[
						126200,
						2,
						0
					],
					[
						126300,
						3,
						0
					]
				],
				"altAnim": false,
				"mustHitSection": true,
				"bpm": 150
			},
			{
				"typeOfSection": 0,
				"lengthInSteps": 16,
				"sectionNotes": [
					[
						126400,
						1,
						0
					],
					[
						126500,
						3,
						0
					],
					[
						126600,
						2,
						0
					],
					[
						126700,
						0,
						0
					],
					[
						126800,
						1,
						0
					],
					[
						127000,
						2,
						0
					],
					[
						127200,
						1,
						0
					],
					[
						127000,
						3,
						0
					],
					[
						127350,
						0,
						0
					],
					[
						127500,
						2,
						0
					],
					[
						127600,
						3,
						0
					],
					[
						127750,
						1,
						0
					],
					[
						127900,
						2,
						0
					],
					[
						126400,
						-1,
						"Add Camera Zoom",
						"",
						""
					],
					[
						126800,
						-1,
						"Add Camera Zoom",
						"",
						""
					],
					[
						127200,
						-1,
						"Add Camera Zoom",
						"",
						""
					],
					[
						127600,
						-1,
						"Add Camera Zoom",
						"",
						""
					]
				],
				"altAnim": false,
				"mustHitSection": true,
				"bpm": 150
			},
			{
				"typeOfSection": 0,
				"lengthInSteps": 16,
				"sectionNotes": [
					[
						128400,
						1,
						0
					],
					[
						128600,
						0,
						0
					],
					[
						128800,
						0,
						0
					],
					[
						129000,
						3,
						0
					],
					[
						129200,
						2,
						0
					],
					[
						128000,
						4,
						800
					]
				],
				"altAnim": false,
				"mustHitSection": false,
				"bpm": 150
			},
			{
				"typeOfSection": 0,
				"lengthInSteps": 16,
				"sectionNotes": [
					[
						129600,
						3,
						0
					],
					[
						129900,
						2,
						0
					],
					[
						129950,
						3,
						0
					],
					[
						130200,
						3,
						300
					],
					[
						130800,
						1,
						500
					],
					[
						129800,
						3,
						0
					],
					[
						130000,
						0,
						0
					],
					[
						130050,
						2,
						0
					],
					[
						130100,
						1,
						0
					],
					[
						130150,
						2,
						0
					]
				],
				"altAnim": false,
				"mustHitSection": false,
				"bpm": 150
			},
			{
				"typeOfSection": 0,
				"lengthInSteps": 16,
				"sectionNotes": [
					[
						131600,
						0,
						0
					],
					[
						131700,
						2,
						0
					],
					[
						131800,
						0,
						0
					],
					[
						131900,
						2,
						0
					],
					[
						132000,
						3,
						0
					],
					[
						132200,
						3,
						0
					],
					[
						132400,
						1,
						0
					]
				],
				"altAnim": false,
				"mustHitSection": false,
				"bpm": 150
			},
			{
				"typeOfSection": 0,
				"lengthInSteps": 16,
				"sectionNotes": [
					[
						132800,
						6,
						0
					],
					[
						132800,
						3,
						300
					],
					[
						133000,
						4,
						0
					],
					[
						133200,
						4,
						0
					],
					[
						133200,
						0,
						300
					],
					[
						133400,
						6,
						0
					],
					[
						133500,
						6,
						0
					],
					[
						133600,
						7,
						0
					],
					[
						133600,
						2,
						100
					],
					[
						133800,
						5,
						0
					],
					[
						133800,
						1,
						100
					],
					[
						134000,
						4,
						0
					],
					[
						134000,
						2,
						300
					],
					[
						134200,
						5,
						0
					],
					[
						134200,
						0,
						100
					]
				],
				"altAnim": false,
				"mustHitSection": true,
				"bpm": 150
			},
			{
				"typeOfSection": 0,
				"lengthInSteps": 16,
				"sectionNotes": [
					[
						134400,
						2,
						0
					],
					[
						134600,
						0,
						0
					],
					[
						134700,
						1,
						0
					],
					[
						134800,
						3,
						0
					],
					[
						134800,
						6,
						0
					],
					[
						135000,
						2,
						0
					],
					[
						135200,
						1,
						0
					],
					[
						135200,
						5,
						0
					],
					[
						135400,
						0,
						0
					],
					[
						135600,
						2,
						0
					],
					[
						134600,
						5,
						0
					],
					[
						135000,
						7,
						0
					],
					[
						135300,
						7,
						0
					],
					[
						135400,
						4,
						0
					],
					[
						135600,
						6,
						0
					],
					[
						135700,
						4,
						0
					],
					[
						135800,
						5,
						0
					],
					[
						134400,
						7,
						0
					]
				],
				"altAnim": false,
				"mustHitSection": false,
				"bpm": 150
			},
			{
				"typeOfSection": 0,
				"lengthInSteps": 16,
				"sectionNotes": [
					[
						136000,
						2,
						0
					],
					[
						136100,
						5,
						0
					],
					[
						136200,
						3,
						0
					],
					[
						136300,
						2,
						0
					],
					[
						136350,
						3,
						0
					],
					[
						136400,
						2,
						0
					],
					[
						136450,
						1,
						0
					],
					[
						136500,
						0,
						0
					],
					[
						136550,
						1,
						0
					],
					[
						136600,
						4,
						0
					],
					[
						136600,
						2,
						400
					],
					[
						137200,
						0,
						300
					],
					[
						136000,
						4,
						0
					],
					[
						136200,
						6,
						0
					],
					[
						136400,
						7,
						0
					],
					[
						136600,
						6,
						0
					],
					[
						136800,
						7,
						0
					],
					[
						137200,
						6,
						0
					],
					[
						137200,
						4,
						0
					],
					[
						137000,
						5,
						0
					],
					[
						137300,
						7,
						0
					],
					[
						137400,
						6,
						0
					]
				],
				"altAnim": false,
				"mustHitSection": false,
				"bpm": 150
			},
			{
				"typeOfSection": 0,
				"lengthInSteps": 16,
				"sectionNotes": [
					[
						138000,
						5,
						0
					],
					[
						138200,
						3,
						0
					],
					[
						138200,
						4,
						0
					],
					[
						138400,
						2,
						0
					],
					[
						138600,
						5,
						0
					],
					[
						139000,
						3,
						0
					],
					[
						137600,
						0,
						0
					],
					[
						137800,
						2,
						0
					],
					[
						138000,
						1,
						0
					],
					[
						138000,
						0,
						0
					],
					[
						138600,
						0,
						0
					],
					[
						138800,
						1,
						0
					],
					[
						138900,
						2,
						0
					]
				],
				"altAnim": false,
				"mustHitSection": true,
				"bpm": 150
			},
			{
				"typeOfSection": 0,
				"lengthInSteps": 16,
				"sectionNotes": [
					[
						139200,
						6,
						0
					],
					[
						139400,
						5,
						0
					],
					[
						139400,
						2,
						0
					],
					[
						139600,
						7,
						0
					],
					[
						139800,
						4,
						0
					],
					[
						139800,
						2,
						0
					],
					[
						140000,
						7,
						0
					],
					[
						140000,
						5,
						0
					],
					[
						140000,
						3,
						0
					],
					[
						140200,
						4,
						0
					],
					[
						140400,
						7,
						0
					],
					[
						140600,
						6,
						0
					],
					[
						139200,
						0,
						0
					],
					[
						139600,
						3,
						0
					],
					[
						140000,
						1,
						0
					],
					[
						140200,
						0,
						0
					],
					[
						140400,
						1,
						0
					],
					[
						140600,
						2,
						0
					]
				],
				"altAnim": false,
				"mustHitSection": true,
				"bpm": 150
			},
			{
				"typeOfSection": 0,
				"lengthInSteps": 16,
				"sectionNotes": [
					[
						140800,
						6,
						0
					],
					[
						140800,
						0,
						200
					],
					[
						140800,
						1,
						300
					],
					[
						141000,
						4,
						0
					],
					[
						141200,
						5,
						0
					],
					[
						141200,
						3,
						0
					],
					[
						141400,
						7,
						0
					],
					[
						141400,
						2,
						0
					],
					[
						141600,
						5,
						0
					],
					[
						141600,
						0,
						0
					],
					[
						141700,
						4,
						0
					],
					[
						141700,
						1,
						0
					],
					[
						141800,
						5,
						0
					],
					[
						141800,
						2,
						0
					],
					[
						142000,
						6,
						0
					],
					[
						142000,
						3,
						0
					],
					[
						142100,
						7,
						0
					],
					[
						142200,
						6,
						0
					],
					[
						142200,
						2,
						0
					]
				],
				"altAnim": false,
				"mustHitSection": true,
				"bpm": 150
			},
			{
				"typeOfSection": 0,
				"lengthInSteps": 16,
				"sectionNotes": [
					[
						142400,
						1,
						200
					],
					[
						142400,
						5,
						0
					],
					[
						142500,
						5,
						0
					],
					[
						142600,
						6,
						0
					],
					[
						142800,
						2,
						0
					],
					[
						142800,
						7,
						0
					],
					[
						143000,
						3,
						0
					],
					[
						143000,
						4,
						0
					],
					[
						143100,
						0,
						0
					],
					[
						143200,
						5,
						0
					],
					[
						143300,
						2,
						0
					],
					[
						143400,
						3,
						0
					],
					[
						143400,
						6,
						0
					],
					[
						143500,
						2,
						0
					],
					[
						143600,
						0,
						100
					],
					[
						143600,
						4,
						300
					],
					[
						143700,
						5,
						100
					],
					[
						143800,
						7,
						100
					],
					[
						143800,
						2,
						0
					],
					[
						143900,
						0,
						0
					],
					[
						143850,
						6,
						100
					]
				],
				"altAnim": false,
				"mustHitSection": true,
				"bpm": 150
			},
			{
				"typeOfSection": 0,
				"lengthInSteps": 16,
				"sectionNotes": [
					[
						144600,
						6,
						0
					],
					[
						144800,
						5,
						300
					],
					[
						144800,
						1,
						0
					],
					[
						145000,
						1,
						0
					],
					[
						145200,
						2,
						0
					],
					[
						145400,
						3,
						0
					],
					[
						144000,
						3,
						0
					],
					[
						144400,
						0,
						0
					],
					[
						144200,
						2,
						0
					],
					[
						144400,
						1,
						0
					],
					[
						144600,
						3,
						0
					],
					[
						144200,
						6,
						0
					],
					[
						144100,
						5,
						0
					],
					[
						144400,
						4,
						0
					],
					[
						144800,
						4,
						100
					],
					[
						145400,
						5,
						0
					],
					[
						145200,
						6,
						0
					],
					[
						144000,
						5,
						0
					]
				],
				"altAnim": false,
				"mustHitSection": false,
				"bpm": 150
			},
			{
				"typeOfSection": 0,
				"lengthInSteps": 16,
				"sectionNotes": [
					[
						145600,
						5,
						0
					],
					[
						145800,
						6,
						0
					],
					[
						146000,
						0,
						0
					],
					[
						146000,
						4,
						0
					],
					[
						146200,
						5,
						0
					],
					[
						146400,
						7,
						0
					],
					[
						146400,
						6,
						0
					],
					[
						146600,
						5,
						0
					],
					[
						146700,
						4,
						200
					],
					[
						145600,
						3,
						0
					],
					[
						146400,
						3,
						0
					],
					[
						146600,
						3,
						0
					],
					[
						147000,
						2,
						0
					],
					[
						146200,
						2,
						0
					],
					[
						146500,
						2,
						0
					],
					[
						146800,
						0,
						0
					],
					[
						147000,
						7,
						0
					]
				],
				"altAnim": false,
				"mustHitSection": true,
				"bpm": 150
			},
			{
				"typeOfSection": 0,
				"lengthInSteps": 16,
				"sectionNotes": [
					[
						147200,
						1,
						0
					],
					[
						147200,
						7,
						700
					],
					[
						147600,
						1,
						0
					],
					[
						147800,
						0,
						0
					],
					[
						148000,
						2,
						0
					],
					[
						148000,
						6,
						100
					],
					[
						148200,
						3,
						0
					],
					[
						148200,
						7,
						0
					],
					[
						148400,
						2,
						0
					],
					[
						148400,
						6,
						0
					],
					[
						148600,
						1,
						0
					],
					[
						148600,
						4,
						0
					]
				],
				"altAnim": false,
				"mustHitSection": false,
				"bpm": 150
			},
			{
				"typeOfSection": 0,
				"lengthInSteps": 16,
				"sectionNotes": [
					[
						148800,
						0,
						0
					],
					[
						148800,
						5,
						300
					],
					[
						149200,
						7,
						0
					],
					[
						149400,
						1,
						0
					],
					[
						149400,
						6,
						0
					],
					[
						149500,
						2,
						0
					],
					[
						149600,
						0,
						200
					],
					[
						149600,
						4,
						300
					],
					[
						150000,
						6,
						300
					]
				],
				"altAnim": false,
				"mustHitSection": false,
				"bpm": 150
			},
			{
				"typeOfSection": 0,
				"lengthInSteps": 16,
				"sectionNotes": [
					[
						150400,
						3,
						200
					],
					[
						150800,
						7,
						0
					],
					[
						150800,
						3,
						0
					],
					[
						151000,
						6,
						0
					],
					[
						151000,
						3,
						0
					],
					[
						151200,
						4,
						0
					],
					[
						151200,
						3,
						200
					],
					[
						151400,
						5,
						0
					],
					[
						151600,
						6,
						0
					],
					[
						151600,
						3,
						200
					],
					[
						151800,
						4,
						0
					]
				],
				"altAnim": false,
				"mustHitSection": true,
				"bpm": 150
			},
			{
				"typeOfSection": 0,
				"lengthInSteps": 16,
				"sectionNotes": [
					[
						152000,
						5,
						600
					],
					[
						152000,
						1,
						200
					],
					[
						152400,
						0,
						200
					],
					[
						152800,
						7,
						300
					],
					[
						152800,
						2,
						0
					],
					[
						152900,
						3,
						0
					],
					[
						153000,
						2,
						0
					],
					[
						153200,
						6,
						0
					],
					[
						153400,
						4,
						0
					],
					[
						153500,
						5,
						0
					],
					[
						153500,
						2,
						0
					],
					[
						153200,
						1,
						200
					],
					[
						153200,
						0,
						100
					],
					[
						153400,
						3,
						0
					]
				],
				"altAnim": false,
				"mustHitSection": true,
				"bpm": 150
			},
			{
				"typeOfSection": 0,
				"lengthInSteps": 16,
				"sectionNotes": [
					[
						153600,
						1,
						200
					],
					[
						153600,
						7,
						700
					],
					[
						154000,
						1,
						0
					],
					[
						154200,
						0,
						0
					],
					[
						154400,
						2,
						0
					],
					[
						154400,
						6,
						100
					],
					[
						154600,
						3,
						0,
						"Hey!"
					],
					[
						154600,
						7,
						0
					],
					[
						154800,
						2,
						0
					],
					[
						154800,
						6,
						0
					],
					[
						155000,
						1,
						0
					],
					[
						155000,
						4,
						0
					],
					[
						154600,
						1,
						0,
						"Hey!"
					],
					[
						154600,
						0,
						0,
						"Hey!"
					]
				],
				"altAnim": false,
				"mustHitSection": true,
				"bpm": 150
			},
			{
				"typeOfSection": 0,
				"lengthInSteps": 16,
				"sectionNotes": [
					[
						155200,
						0,
						0
					],
					[
						155200,
						5,
						300
					],
					[
						155600,
						7,
						0
					],
					[
						155800,
						1,
						0
					],
					[
						155800,
						6,
						0
					],
					[
						155900,
						2,
						0
					],
					[
						156000,
						4,
						300
					],
					[
						156400,
						6,
						300
					],
					[
						156000,
						3,
						700
					]
				],
				"altAnim": false,
				"mustHitSection": true,
				"bpm": 150
			},
			{
				"typeOfSection": 0,
				"lengthInSteps": 16,
				"sectionNotes": [
					[
						156800,
						3,
						200
					],
					[
						157200,
						3,
						0
					],
					[
						157400,
						6,
						0
					],
					[
						157400,
						3,
						0
					],
					[
						157600,
						3,
						200
					],
					[
						157800,
						5,
						0
					],
					[
						158000,
						6,
						0
					],
					[
						158000,
						3,
						200
					],
					[
						158200,
						4,
						0
					],
					[
						157200,
						4,
						0
					],
					[
						157600,
						4,
						0
					]
				],
				"altAnim": false,
				"mustHitSection": false,
				"bpm": 150
			},
			{
				"typeOfSection": 0,
				"lengthInSteps": 16,
				"sectionNotes": [
					[
						158400,
						5,
						600
					],
					[
						158400,
						1,
						200
					],
					[
						158800,
						0,
						200
					],
					[
						159200,
						7,
						300
					],
					[
						159200,
						2,
						0
					],
					[
						159300,
						3,
						0
					],
					[
						159400,
						2,
						0
					],
					[
						159600,
						6,
						0
					],
					[
						159600,
						3,
						0
					],
					[
						159800,
						4,
						0
					],
					[
						159800,
						0,
						0
					],
					[
						159900,
						5,
						0
					],
					[
						159900,
						1,
						0
					]
				],
				"altAnim": false,
				"mustHitSection": false,
				"bpm": 150
			},
			{
				"typeOfSection": 0,
				"lengthInSteps": 16,
				"sectionNotes": [
					[
						160400,
						1,
						0
					],
					[
						160600,
						3,
						0
					],
					[
						160800,
						2,
						0
					],
					[
						161000,
						1,
						0
					],
					[
						161000,
						0,
						0
					],
					[
						161200,
						3,
						200
					]
				],
				"altAnim": false,
				"mustHitSection": false,
				"bpm": 150
			},
			{
				"typeOfSection": 0,
				"lengthInSteps": 16,
				"sectionNotes": [
					[
						161600,
						2,
						0
					],
					[
						161800,
						1,
						0
					],
					[
						161900,
						0,
						0
					],
					[
						161950,
						1,
						0
					],
					[
						162000,
						2,
						0
					],
					[
						162100,
						3,
						0
					],
					[
						162150,
						2,
						0
					],
					[
						162800,
						1,
						0
					],
					[
						162200,
						0,
						500
					]
				],
				"altAnim": false,
				"mustHitSection": false,
				"bpm": 150
			},
			{
				"typeOfSection": 0,
				"lengthInSteps": 16,
				"sectionNotes": [
					[
						163600,
						0,
						0
					],
					[
						163800,
						3,
						0
					],
					[
						164200,
						1,
						0
					]
				],
				"altAnim": false,
				"mustHitSection": false,
				"bpm": 150
			},
			{
				"typeOfSection": 0,
				"lengthInSteps": 16,
				"sectionNotes": [
					[
						164800,
						3,
						0
					],
					[
						165000,
						2,
						0
					],
					[
						165200,
						0,
						0
					],
					[
						165400,
						2,
						0
					],
					[
						165600,
						3,
						0
					],
					[
						165800,
						1,
						0
					],
					[
						166000,
						0,
						0
					],
					[
						166200,
						1,
						0
					]
				],
				"altAnim": false,
				"mustHitSection": false,
				"bpm": 150
			},
			{
				"typeOfSection": 0,
				"lengthInSteps": 16,
				"sectionNotes": [
					[
						166400,
						7,
						300
					],
					[
						166800,
						1,
						0
					],
					[
						167000,
						3,
						0
					],
					[
						167200,
						2,
						0
					],
					[
						167400,
						1,
						0
					],
					[
						167600,
						0,
						200
					]
				],
				"altAnim": false,
				"mustHitSection": true,
				"bpm": 150
			},
			{
				"typeOfSection": 0,
				"lengthInSteps": 16,
				"sectionNotes": [
					[
						168000,
						2,
						0
					],
					[
						168200,
						1,
						0
					],
					[
						168300,
						0,
						0
					],
					[
						168350,
						1,
						0
					],
					[
						168400,
						2,
						0
					],
					[
						168500,
						3,
						0
					],
					[
						168550,
						2,
						0
					],
					[
						168600,
						0,
						500
					],
					[
						169200,
						2,
						0
					]
				],
				"altAnim": false,
				"mustHitSection": true,
				"bpm": 150
			},
			{
				"typeOfSection": 0,
				"lengthInSteps": 16,
				"sectionNotes": [
					[
						170000,
						3,
						0
					],
					[
						170200,
						0,
						0
					],
					[
						170600,
						2,
						0
					]
				],
				"altAnim": false,
				"mustHitSection": true,
				"bpm": 150
			},
			{
				"typeOfSection": 0,
				"lengthInSteps": 16,
				"sectionNotes": [
					[
						171200,
						3,
						0
					],
					[
						171400,
						1,
						0
					],
					[
						171600,
						3,
						0
					],
					[
						171800,
						1,
						0
					],
					[
						172000,
						3,
						0
					],
					[
						172200,
						0,
						0
					],
					[
						172200,
						1,
						0
					],
					[
						172400,
						3,
						0
					],
					[
						172600,
						2,
						0
					]
				],
				"altAnim": false,
				"mustHitSection": true,
				"bpm": 150
			},
			{
				"typeOfSection": 0,
				"lengthInSteps": 16,
				"sectionNotes": [
					[
						173200,
						1,
						0
					],
					[
						173400,
						3,
						0
					],
					[
						173600,
						2,
						0
					],
					[
						173800,
						1,
						0
					],
					[
						173800,
						0,
						0
					],
					[
						174000,
						3,
						200
					],
					[
						172800,
						4,
						400
					]
				],
				"altAnim": false,
				"mustHitSection": false,
				"bpm": 150
			},
			{
				"typeOfSection": 0,
				"lengthInSteps": 16,
				"sectionNotes": [
					[
						174400,
						2,
						0
					],
					[
						174600,
						1,
						0
					],
					[
						174700,
						0,
						0
					],
					[
						174750,
						1,
						0
					],
					[
						174800,
						2,
						0
					],
					[
						174900,
						3,
						0
					],
					[
						174950,
						2,
						0
					],
					[
						175600,
						1,
						0
					],
					[
						175000,
						0,
						500
					]
				],
				"altAnim": false,
				"mustHitSection": false,
				"bpm": 150
			},
			{
				"typeOfSection": 0,
				"lengthInSteps": 16,
				"sectionNotes": [
					[
						176400,
						2,
						0
					],
					[
						176400,
						5,
						0
					],
					[
						176600,
						3,
						0
					],
					[
						176600,
						4,
						0
					],
					[
						177000,
						2,
						300
					],
					[
						177000,
						5,
						300
					]
				],
				"altAnim": false,
				"mustHitSection": true,
				"bpm": 150
			},
			{
				"typeOfSection": 0,
				"lengthInSteps": 16,
				"sectionNotes": [
					[
						177600,
						3,
						0
					],
					[
						177800,
						1,
						0
					],
					[
						178000,
						3,
						0
					],
					[
						178200,
						1,
						0
					],
					[
						178400,
						3,
						0
					],
					[
						178600,
						0,
						0
					],
					[
						178600,
						1,
						0
					],
					[
						178800,
						3,
						0
					],
					[
						179000,
						1,
						0
					],
					[
						177600,
						5,
						0
					],
					[
						178000,
						6,
						0
					],
					[
						178400,
						5,
						0
					],
					[
						178400,
						4,
						0
					],
					[
						178800,
						6,
						0
					]
				],
				"altAnim": false,
				"mustHitSection": true,
				"bpm": 150
			},
			{
				"typeOfSection": 0,
				"lengthInSteps": 16,
				"sectionNotes": [
					[
						179200,
						2,
						100
					],
					[
						179400,
						3,
						100
					],
					[
						179600,
						2,
						1100
					],
					[
						179600,
						0,
						700
					],
					[
						179200,
						7,
						0
					],
					[
						179200,
						5,
						0
					]
				],
				"altAnim": false,
				"mustHitSection": true,
				"bpm": 150
			},
			{
				"typeOfSection": 0,
				"lengthInSteps": 16,
				"sectionNotes": [
					[
						180800,
						1,
						0
					],
					[
						180800,
						3,
						0
					],
					[
						181000,
						0,
						0
					],
					[
						181200,
						2,
						0
					],
					[
						181400,
						3,
						0
					],
					[
						181600,
						0,
						300
					],
					[
						182000,
						3,
						300
					],
					[
						181000,
						5,
						0
					],
					[
						181200,
						6,
						0
					],
					[
						181400,
						7,
						0
					],
					[
						181600,
						4,
						0
					],
					[
						181800,
						6,
						0
					],
					[
						182000,
						5,
						0
					]
				],
				"altAnim": false,
				"mustHitSection": true,
				"bpm": 150
			},
			{
				"typeOfSection": 0,
				"lengthInSteps": 16,
				"sectionNotes": [],
				"altAnim": false,
				"mustHitSection": true,
				"bpm": 150
			},
			{
				"typeOfSection": 0,
				"lengthInSteps": 16,
				"sectionNotes": [],
				"altAnim": false,
				"mustHitSection": true,
				"bpm": 150
			},
			{
				"typeOfSection": 0,
				"lengthInSteps": 16,
				"sectionNotes": [],
				"altAnim": false,
				"mustHitSection": true,
				"bpm": 150
			},
			{
				"typeOfSection": 0,
				"lengthInSteps": 16,
				"sectionNotes": [],
				"altAnim": false,
				"mustHitSection": true,
				"bpm": 150
			},
			{
				"typeOfSection": 0,
				"lengthInSteps": 16,
				"sectionNotes": [],
				"altAnim": false,
				"mustHitSection": true,
				"bpm": 150
			},
			{
				"typeOfSection": 0,
				"lengthInSteps": 16,
				"sectionNotes": [],
				"altAnim": false,
				"mustHitSection": true,
				"bpm": 150
			},
			{
				"typeOfSection": 0,
				"lengthInSteps": 16,
				"sectionNotes": [],
				"altAnim": false,
				"mustHitSection": true,
				"bpm": 150
			},
			{
				"typeOfSection": 0,
				"lengthInSteps": 16,
				"sectionNotes": [],
				"altAnim": false,
				"mustHitSection": true,
				"bpm": 150
			},
			{
				"typeOfSection": 0,
				"lengthInSteps": 16,
				"sectionNotes": [],
				"altAnim": false,
				"mustHitSection": true,
				"bpm": 150
			},
			{
				"typeOfSection": 0,
				"lengthInSteps": 16,
				"sectionNotes": [],
				"altAnim": false,
				"mustHitSection": true,
				"bpm": 150
			},
			{
				"typeOfSection": 0,
				"lengthInSteps": 16,
				"sectionNotes": [],
				"altAnim": false,
				"mustHitSection": true,
				"bpm": 150
			},
			{
				"typeOfSection": 0,
				"lengthInSteps": 16,
				"sectionNotes": [],
				"altAnim": false,
				"mustHitSection": true,
				"bpm": 150
			},
			{
				"typeOfSection": 0,
				"lengthInSteps": 16,
				"sectionNotes": [],
				"altAnim": false,
				"mustHitSection": true,
				"bpm": 150
			},
			{
				"typeOfSection": 0,
				"lengthInSteps": 16,
				"sectionNotes": [],
				"altAnim": false,
				"mustHitSection": true,
				"bpm": 150
			},
			{
				"typeOfSection": 0,
				"lengthInSteps": 16,
				"sectionNotes": [],
				"altAnim": false,
				"mustHitSection": true,
				"bpm": 150
			},
			{
				"typeOfSection": 0,
				"lengthInSteps": 16,
				"sectionNotes": [],
				"altAnim": false,
				"mustHitSection": true,
				"bpm": 150
			},
			{
				"typeOfSection": 0,
				"lengthInSteps": 16,
				"sectionNotes": [],
				"altAnim": false,
				"mustHitSection": true,
				"bpm": 150
			},
			{
				"typeOfSection": 0,
				"lengthInSteps": 16,
				"sectionNotes": [],
				"altAnim": false,
				"mustHitSection": true,
				"bpm": 150
			},
			{
				"typeOfSection": 0,
				"lengthInSteps": 16,
				"sectionNotes": [],
				"altAnim": false,
				"mustHitSection": true,
				"bpm": 150
			},
			{
				"typeOfSection": 0,
				"lengthInSteps": 16,
				"sectionNotes": [],
				"altAnim": false,
				"mustHitSection": true,
				"bpm": 150
			},
			{
				"typeOfSection": 0,
				"lengthInSteps": 16,
				"sectionNotes": [],
				"altAnim": false,
				"mustHitSection": true,
				"bpm": 150
			},
			{
				"lengthInSteps": 16,
				"sectionNotes": [],
				"typeOfSection": 0,
				"altAnim": false,
				"mustHitSection": true,
				"changeBPM": false,
				"bpm": 150
			},
			{
				"lengthInSteps": 16,
				"sectionNotes": [],
				"typeOfSection": 0,
				"altAnim": false,
				"mustHitSection": true,
				"changeBPM": false,
				"bpm": 150
			},
			{
				"lengthInSteps": 16,
				"sectionNotes": [],
				"typeOfSection": 0,
				"altAnim": false,
				"mustHitSection": true,
				"changeBPM": false,
				"bpm": 150
			},
			{
				"lengthInSteps": 16,
				"sectionNotes": [],
				"typeOfSection": 0,
				"altAnim": false,
				"mustHitSection": true,
				"changeBPM": false,
				"bpm": 150
			},
			{
				"lengthInSteps": 16,
				"sectionNotes": [],
				"typeOfSection": 0,
				"altAnim": false,
				"mustHitSection": true,
				"changeBPM": false,
				"bpm": 150
			},
			{
				"lengthInSteps": 16,
				"sectionNotes": [],
				"typeOfSection": 0,
				"altAnim": false,
				"mustHitSection": true,
				"changeBPM": false,
				"bpm": 150
			},
			{
				"lengthInSteps": 16,
				"sectionNotes": [],
				"typeOfSection": 0,
				"altAnim": false,
				"mustHitSection": true,
				"changeBPM": false,
				"bpm": 150
			},
			{
				"lengthInSteps": 16,
				"sectionNotes": [],
				"typeOfSection": 0,
				"altAnim": false,
				"mustHitSection": true,
				"changeBPM": false,
				"bpm": 150
			},
			{
				"lengthInSteps": 16,
				"sectionNotes": [],
				"typeOfSection": 0,
				"altAnim": false,
				"mustHitSection": true,
				"changeBPM": false,
				"bpm": 150
			},
			{
				"lengthInSteps": 16,
				"sectionNotes": [],
				"typeOfSection": 0,
				"altAnim": false,
				"mustHitSection": true,
				"changeBPM": false,
				"bpm": 150
			},
			{
				"lengthInSteps": 16,
				"sectionNotes": [],
				"typeOfSection": 0,
				"altAnim": false,
				"mustHitSection": true,
				"changeBPM": false,
				"bpm": 150
			},
			{
				"sectionNotes": [],
				"typeOfSection": 0,
				"lengthInSteps": 16,
				"altAnim": false,
				"mustHitSection": true,
				"changeBPM": false,
				"bpm": 150
			},
			{
				"sectionNotes": [],
				"typeOfSection": 0,
				"lengthInSteps": 16,
				"altAnim": false,
				"mustHitSection": true,
				"changeBPM": false,
				"bpm": 150
			},
			{
				"sectionNotes": [],
				"typeOfSection": 0,
				"lengthInSteps": 16,
				"altAnim": false,
				"mustHitSection": true,
				"changeBPM": false,
				"bpm": 150
			},
			{
				"sectionNotes": [],
				"typeOfSection": 0,
				"lengthInSteps": 16,
				"altAnim": false,
				"mustHitSection": true,
				"changeBPM": false,
				"bpm": 150
			},
			{
				"sectionNotes": [],
				"typeOfSection": 0,
				"lengthInSteps": 16,
				"altAnim": false,
				"mustHitSection": true,
				"changeBPM": false,
				"bpm": 150
			},
			{
				"sectionNotes": [],
				"typeOfSection": 0,
				"lengthInSteps": 16,
				"altAnim": false,
				"mustHitSection": true,
				"changeBPM": false,
				"bpm": 150
			},
			{
				"sectionNotes": [],
				"typeOfSection": 0,
				"lengthInSteps": 16,
				"altAnim": false,
				"mustHitSection": true,
				"changeBPM": false,
				"bpm": 150
			},
			{
				"lengthInSteps": 16,
				"typeOfSection": 0,
				"sectionNotes": [],
				"altAnim": false,
				"bpm": 150,
				"changeBPM": false,
				"mustHitSection": true
			},
			{
				"lengthInSteps": 16,
				"typeOfSection": 0,
				"sectionNotes": [],
				"altAnim": false,
				"bpm": 150,
				"changeBPM": false,
				"mustHitSection": true
			},
			{
				"lengthInSteps": 16,
				"typeOfSection": 0,
				"sectionNotes": [],
				"altAnim": false,
				"bpm": 150,
				"changeBPM": false,
				"mustHitSection": true
			},
			{
				"lengthInSteps": 16,
				"typeOfSection": 0,
				"sectionNotes": [],
				"altAnim": false,
				"bpm": 150,
				"changeBPM": false,
				"mustHitSection": true
			},
			{
				"lengthInSteps": 16,
				"typeOfSection": 0,
				"sectionNotes": [],
				"altAnim": false,
				"bpm": 150,
				"changeBPM": false,
				"mustHitSection": true
			},
			{
				"lengthInSteps": 16,
				"typeOfSection": 0,
				"sectionNotes": [],
				"altAnim": false,
				"bpm": 150,
				"changeBPM": false,
				"mustHitSection": true
			},
			{
				"lengthInSteps": 16,
				"typeOfSection": 0,
				"sectionNotes": [],
				"altAnim": false,
				"bpm": 150,
				"changeBPM": false,
				"mustHitSection": true
			},
			{
				"sectionNotes": [],
				"typeOfSection": 0,
				"lengthInSteps": 16,
				"altAnim": false,
				"mustHitSection": true,
				"changeBPM": false,
				"bpm": 150
			},
			{
				"sectionNotes": [],
				"typeOfSection": 0,
				"lengthInSteps": 16,
				"altAnim": false,
				"mustHitSection": true,
				"changeBPM": false,
				"bpm": 150
			},
			{
				"sectionNotes": [],
				"typeOfSection": 0,
				"lengthInSteps": 16,
				"altAnim": false,
				"mustHitSection": true,
				"changeBPM": false,
				"bpm": 150
			},
			{
				"lengthInSteps": 16,
				"typeOfSection": 0,
				"sectionNotes": [],
				"altAnim": false,
				"bpm": 150,
				"changeBPM": false,
				"mustHitSection": true
			},
			{
				"lengthInSteps": 16,
				"typeOfSection": 0,
				"sectionNotes": [],
				"altAnim": false,
				"bpm": 150,
				"changeBPM": false,
				"mustHitSection": true
			},
			{
				"lengthInSteps": 16,
				"typeOfSection": 0,
				"sectionNotes": [],
				"altAnim": false,
				"bpm": 150,
				"changeBPM": false,
				"mustHitSection": true
			},
			{
				"lengthInSteps": 16,
				"typeOfSection": 0,
				"sectionNotes": [],
				"altAnim": false,
				"bpm": 150,
				"changeBPM": false,
				"mustHitSection": true
			},
			{
				"lengthInSteps": 16,
				"typeOfSection": 0,
				"sectionNotes": [],
				"altAnim": false,
				"bpm": 150,
				"changeBPM": false,
				"mustHitSection": true
			},
			{
				"lengthInSteps": 16,
				"typeOfSection": 0,
				"sectionNotes": [],
				"altAnim": false,
				"bpm": 150,
				"changeBPM": false,
				"mustHitSection": true
			},
			{
				"lengthInSteps": 16,
				"typeOfSection": 0,
				"sectionNotes": [],
				"altAnim": false,
				"bpm": 150,
				"changeBPM": false,
				"mustHitSection": true
			},
			{
				"sectionNotes": [],
				"typeOfSection": 0,
				"lengthInSteps": 16,
				"altAnim": false,
				"mustHitSection": true,
				"changeBPM": false,
				"bpm": 150
			},
			{
				"sectionNotes": [],
				"typeOfSection": 0,
				"lengthInSteps": 16,
				"altAnim": false,
				"mustHitSection": true,
				"changeBPM": false,
				"bpm": 150
			},
			{
				"sectionNotes": [],
				"typeOfSection": 0,
				"lengthInSteps": 16,
				"altAnim": false,
				"mustHitSection": true,
				"changeBPM": false,
				"bpm": 150
			},
			{
				"lengthInSteps": 16,
				"typeOfSection": 0,
				"sectionNotes": [],
				"altAnim": false,
				"bpm": 150,
				"changeBPM": false,
				"mustHitSection": true
			},
			{
				"lengthInSteps": 16,
				"typeOfSection": 0,
				"sectionNotes": [],
				"altAnim": false,
				"bpm": 150,
				"changeBPM": false,
				"mustHitSection": true
			},
			{
				"lengthInSteps": 16,
				"typeOfSection": 0,
				"sectionNotes": [],
				"altAnim": false,
				"bpm": 150,
				"changeBPM": false,
				"mustHitSection": true
			},
			{
				"lengthInSteps": 16,
				"typeOfSection": 0,
				"sectionNotes": [],
				"altAnim": false,
				"bpm": 150,
				"changeBPM": false,
				"mustHitSection": true
			},
			{
				"sectionNotes": [],
				"typeOfSection": 0,
				"lengthInSteps": 16,
				"altAnim": false,
				"mustHitSection": true,
				"changeBPM": false,
				"bpm": 150
			},
			{
				"sectionNotes": [],
				"typeOfSection": 0,
				"lengthInSteps": 16,
				"altAnim": false,
				"mustHitSection": true,
				"changeBPM": false,
				"bpm": 150
			},
			{
				"sectionNotes": [],
				"typeOfSection": 0,
				"lengthInSteps": 16,
				"altAnim": false,
				"mustHitSection": true,
				"changeBPM": false,
				"bpm": 150
			},
			{
				"sectionNotes": [],
				"typeOfSection": 0,
				"lengthInSteps": 16,
				"altAnim": false,
				"mustHitSection": true,
				"changeBPM": false,
				"bpm": 150
			},
			{
				"sectionNotes": [],
				"typeOfSection": 0,
				"lengthInSteps": 16,
				"altAnim": false,
				"mustHitSection": true,
				"changeBPM": false,
				"bpm": 150
			},
			{
				"sectionNotes": [],
				"typeOfSection": 0,
				"lengthInSteps": 16,
				"altAnim": false,
				"mustHitSection": true,
				"changeBPM": false,
				"bpm": 150
			},
			{
				"sectionNotes": [],
				"typeOfSection": 0,
				"lengthInSteps": 16,
				"altAnim": false,
				"mustHitSection": true,
				"changeBPM": false,
				"bpm": 150
			},
			{
				"lengthInSteps": 16,
				"typeOfSection": 0,
				"sectionNotes": [],
				"altAnim": false,
				"bpm": 150,
				"changeBPM": false,
				"mustHitSection": true
			},
			{
				"lengthInSteps": 16,
				"typeOfSection": 0,
				"sectionNotes": [],
				"altAnim": false,
				"bpm": 150,
				"changeBPM": false,
				"mustHitSection": true
			},
			{
				"lengthInSteps": 16,
				"typeOfSection": 0,
				"sectionNotes": [],
				"altAnim": false,
				"bpm": 150,
				"changeBPM": false,
				"mustHitSection": true
			},
			{
				"lengthInSteps": 16,
				"typeOfSection": 0,
				"sectionNotes": [],
				"altAnim": false,
				"bpm": 150,
				"changeBPM": false,
				"mustHitSection": true
			},
			{
				"lengthInSteps": 16,
				"typeOfSection": 0,
				"sectionNotes": [],
				"altAnim": false,
				"bpm": 150,
				"changeBPM": false,
				"mustHitSection": true
			},
			{
				"lengthInSteps": 16,
				"typeOfSection": 0,
				"sectionNotes": [],
				"altAnim": false,
				"bpm": 150,
				"changeBPM": false,
				"mustHitSection": true
			},
			{
				"lengthInSteps": 16,
				"typeOfSection": 0,
				"sectionNotes": [],
				"altAnim": false,
				"bpm": 150,
				"changeBPM": false,
				"mustHitSection": true
			},
			{
				"lengthInSteps": 16,
				"typeOfSection": 0,
				"sectionNotes": [],
				"altAnim": false,
				"bpm": 150,
				"changeBPM": false,
				"mustHitSection": true
			},
			{
				"lengthInSteps": 16,
				"typeOfSection": 0,
				"sectionNotes": [],
				"altAnim": false,
				"bpm": 150,
				"changeBPM": false,
				"mustHitSection": true
			},
			{
				"lengthInSteps": 16,
				"typeOfSection": 0,
				"sectionNotes": [],
				"altAnim": false,
				"bpm": 150,
				"changeBPM": false,
				"mustHitSection": true
			},
			{
				"lengthInSteps": 16,
				"typeOfSection": 0,
				"sectionNotes": [],
				"altAnim": false,
				"bpm": 150,
				"changeBPM": false,
				"mustHitSection": true
			},
			{
				"sectionNotes": [],
				"typeOfSection": 0,
				"lengthInSteps": 16,
				"altAnim": false,
				"mustHitSection": true,
				"changeBPM": false,
				"bpm": 150
			},
			{
				"sectionNotes": [],
				"typeOfSection": 0,
				"lengthInSteps": 16,
				"altAnim": false,
				"mustHitSection": true,
				"changeBPM": false,
				"bpm": 150
			},
			{
				"sectionNotes": [],
				"typeOfSection": 0,
				"lengthInSteps": 16,
				"altAnim": false,
				"mustHitSection": true,
				"changeBPM": false,
				"bpm": 150
			},
			{
				"lengthInSteps": 16,
				"typeOfSection": 0,
				"sectionNotes": [],
				"altAnim": false,
				"bpm": 150,
				"changeBPM": false,
				"mustHitSection": true
			},
			{
				"lengthInSteps": 16,
				"typeOfSection": 0,
				"sectionNotes": [],
				"altAnim": false,
				"bpm": 150,
				"changeBPM": false,
				"mustHitSection": true
			},
			{
				"lengthInSteps": 16,
				"typeOfSection": 0,
				"sectionNotes": [],
				"altAnim": false,
				"bpm": 150,
				"changeBPM": false,
				"mustHitSection": true
			},
			{
				"lengthInSteps": 16,
				"typeOfSection": 0,
				"sectionNotes": [],
				"altAnim": false,
				"bpm": 150,
				"changeBPM": false,
				"mustHitSection": true
			},
			{
				"lengthInSteps": 16,
				"typeOfSection": 0,
				"sectionNotes": [],
				"altAnim": false,
				"bpm": 150,
				"changeBPM": false,
				"mustHitSection": true
			},
			{
				"lengthInSteps": 16,
				"typeOfSection": 0,
				"sectionNotes": [],
				"altAnim": false,
				"bpm": 150,
				"changeBPM": false,
				"mustHitSection": true
			},
			{
				"lengthInSteps": 16,
				"typeOfSection": 0,
				"sectionNotes": [],
				"altAnim": false,
				"bpm": 150,
				"changeBPM": false,
				"mustHitSection": true
			},
			{
				"lengthInSteps": 16,
				"typeOfSection": 0,
				"sectionNotes": [],
				"altAnim": false,
				"bpm": 150,
				"changeBPM": false,
				"mustHitSection": true
			},
			{
				"lengthInSteps": 16,
				"typeOfSection": 0,
				"sectionNotes": [],
				"altAnim": false,
				"bpm": 150,
				"changeBPM": false,
				"mustHitSection": true
			},
			{
				"lengthInSteps": 16,
				"typeOfSection": 0,
				"sectionNotes": [],
				"altAnim": false,
				"bpm": 150,
				"changeBPM": false,
				"mustHitSection": true
			},
			{
				"sectionNotes": [],
				"typeOfSection": 0,
				"lengthInSteps": 16,
				"altAnim": false,
				"mustHitSection": true,
				"changeBPM": false,
				"bpm": 150
			},
			{
				"lengthInSteps": 16,
				"typeOfSection": 0,
				"sectionNotes": [],
				"altAnim": false,
				"bpm": 150,
				"changeBPM": false,
				"mustHitSection": true
			},
			{
				"lengthInSteps": 16,
				"typeOfSection": 0,
				"sectionNotes": [],
				"altAnim": false,
				"bpm": 150,
				"changeBPM": false,
				"mustHitSection": true
			},
			{
				"lengthInSteps": 16,
				"typeOfSection": 0,
				"sectionNotes": [],
				"altAnim": false,
				"bpm": 150,
				"changeBPM": false,
				"mustHitSection": true
			},
			{
				"lengthInSteps": 16,
				"typeOfSection": 0,
				"sectionNotes": [],
				"altAnim": false,
				"bpm": 150,
				"changeBPM": false,
				"mustHitSection": true
			},
			{
				"lengthInSteps": 16,
				"typeOfSection": 0,
				"sectionNotes": [],
				"altAnim": false,
				"bpm": 150,
				"changeBPM": false,
				"mustHitSection": true
			},
			{
				"lengthInSteps": 16,
				"typeOfSection": 0,
				"sectionNotes": [],
				"altAnim": false,
				"bpm": 150,
				"changeBPM": false,
				"mustHitSection": true
			},
			{
				"lengthInSteps": 16,
				"typeOfSection": 0,
				"sectionNotes": [],
				"altAnim": false,
				"bpm": 150,
				"changeBPM": false,
				"mustHitSection": true
			},
			{
				"lengthInSteps": 16,
				"typeOfSection": 0,
				"sectionNotes": [],
				"altAnim": false,
				"bpm": 150,
				"changeBPM": false,
				"mustHitSection": true
			},
			{
				"lengthInSteps": 16,
				"typeOfSection": 0,
				"sectionNotes": [],
				"altAnim": false,
				"bpm": 150,
				"changeBPM": false,
				"mustHitSection": true
			},
			{
				"lengthInSteps": 16,
				"typeOfSection": 0,
				"sectionNotes": [],
				"altAnim": false,
				"bpm": 150,
				"changeBPM": false,
				"mustHitSection": true
			},
			{
				"lengthInSteps": 16,
				"typeOfSection": 0,
				"sectionNotes": [],
				"altAnim": false,
				"bpm": 150,
				"changeBPM": false,
				"mustHitSection": true
			},
			{
				"lengthInSteps": 16,
				"typeOfSection": 0,
				"sectionNotes": [],
				"altAnim": false,
				"bpm": 150,
				"changeBPM": false,
				"mustHitSection": true
			},
			{
				"lengthInSteps": 16,
				"typeOfSection": 0,
				"sectionNotes": [],
				"altAnim": false,
				"bpm": 150,
				"changeBPM": false,
				"mustHitSection": true
			},
			{
				"sectionNotes": [],
				"typeOfSection": 0,
				"lengthInSteps": 16,
				"altAnim": false,
				"mustHitSection": true,
				"changeBPM": false,
				"bpm": 150
			},
			{
				"sectionNotes": [],
				"typeOfSection": 0,
				"lengthInSteps": 16,
				"altAnim": false,
				"mustHitSection": true,
				"changeBPM": false,
				"bpm": 150
			},
			{
				"sectionNotes": [],
				"typeOfSection": 0,
				"lengthInSteps": 16,
				"altAnim": false,
				"mustHitSection": true,
				"changeBPM": false,
				"bpm": 150
			},
			{
				"sectionNotes": [],
				"typeOfSection": 0,
				"lengthInSteps": 16,
				"altAnim": false,
				"mustHitSection": true,
				"changeBPM": false,
				"bpm": 150
			},
			{
				"sectionNotes": [],
				"typeOfSection": 0,
				"lengthInSteps": 16,
				"altAnim": false,
				"mustHitSection": true,
				"changeBPM": false,
				"bpm": 150
			},
			{
				"sectionNotes": [],
				"typeOfSection": 0,
				"lengthInSteps": 16,
				"altAnim": false,
				"mustHitSection": true,
				"changeBPM": false,
				"bpm": 150
			},
			{
				"sectionNotes": [],
				"typeOfSection": 0,
				"lengthInSteps": 16,
				"altAnim": false,
				"mustHitSection": true,
				"changeBPM": false,
				"bpm": 150
			},
			{
				"sectionNotes": [],
				"typeOfSection": 0,
				"lengthInSteps": 16,
				"altAnim": false,
				"mustHitSection": true,
				"changeBPM": false,
				"bpm": 150
			},
			{
				"sectionNotes": [],
				"typeOfSection": 0,
				"lengthInSteps": 16,
				"altAnim": false,
				"mustHitSection": true,
				"changeBPM": false,
				"bpm": 150
			},
			{
				"sectionNotes": [],
				"typeOfSection": 0,
				"lengthInSteps": 16,
				"altAnim": false,
				"mustHitSection": true,
				"changeBPM": false,
				"bpm": 150
			},
			{
				"sectionNotes": [],
				"typeOfSection": 0,
				"lengthInSteps": 16,
				"altAnim": false,
				"mustHitSection": true,
				"changeBPM": false,
				"bpm": 150
			},
			{
				"sectionNotes": [],
				"typeOfSection": 0,
				"lengthInSteps": 16,
				"altAnim": false,
				"mustHitSection": true,
				"changeBPM": false,
				"bpm": 150
			},
			{
				"sectionNotes": [],
				"typeOfSection": 0,
				"lengthInSteps": 16,
				"altAnim": false,
				"mustHitSection": true,
				"changeBPM": false,
				"bpm": 150
			},
			{
				"sectionNotes": [],
				"typeOfSection": 0,
				"lengthInSteps": 16,
				"altAnim": false,
				"mustHitSection": true,
				"changeBPM": false,
				"bpm": 150
			},
			{
				"sectionNotes": [],
				"typeOfSection": 0,
				"lengthInSteps": 16,
				"altAnim": false,
				"mustHitSection": true,
				"changeBPM": false,
				"bpm": 150
			},
			{
				"sectionNotes": [],
				"typeOfSection": 0,
				"lengthInSteps": 16,
				"altAnim": false,
				"mustHitSection": true,
				"changeBPM": false,
				"bpm": 150
			},
			{
				"sectionNotes": [],
				"typeOfSection": 0,
				"lengthInSteps": 16,
				"altAnim": false,
				"mustHitSection": true,
				"changeBPM": false,
				"bpm": 150
			},
			{
				"lengthInSteps": 16,
				"typeOfSection": 0,
				"sectionNotes": [],
				"altAnim": false,
				"bpm": 150,
				"changeBPM": false,
				"mustHitSection": true
			},
			{
				"lengthInSteps": 16,
				"typeOfSection": 0,
				"sectionNotes": [],
				"altAnim": false,
				"bpm": 150,
				"changeBPM": false,
				"mustHitSection": true
			},
			{
				"lengthInSteps": 16,
				"typeOfSection": 0,
				"sectionNotes": [],
				"altAnim": false,
				"bpm": 150,
				"changeBPM": false,
				"mustHitSection": true
			},
			{
				"lengthInSteps": 16,
				"typeOfSection": 0,
				"sectionNotes": [],
				"altAnim": false,
				"bpm": 150,
				"changeBPM": false,
				"mustHitSection": true
			},
			{
				"lengthInSteps": 16,
				"typeOfSection": 0,
				"sectionNotes": [],
				"altAnim": false,
				"bpm": 150,
				"changeBPM": false,
				"mustHitSection": true
			},
			{
				"sectionNotes": [],
				"typeOfSection": 0,
				"lengthInSteps": 16,
				"altAnim": false,
				"mustHitSection": true,
				"changeBPM": false,
				"bpm": 150
			},
			{
				"sectionNotes": [],
				"typeOfSection": 0,
				"lengthInSteps": 16,
				"altAnim": false,
				"mustHitSection": true,
				"changeBPM": false,
				"bpm": 150
			},
			{
				"sectionNotes": [],
				"typeOfSection": 0,
				"lengthInSteps": 16,
				"altAnim": false,
				"mustHitSection": true,
				"changeBPM": false,
				"bpm": 150
			},
			{
				"lengthInSteps": 16,
				"typeOfSection": 0,
				"sectionNotes": [],
				"altAnim": false,
				"bpm": 150,
				"changeBPM": false,
				"mustHitSection": true
			},
			{
				"lengthInSteps": 16,
				"typeOfSection": 0,
				"sectionNotes": [],
				"altAnim": false,
				"bpm": 150,
				"changeBPM": false,
				"mustHitSection": true
			},
			{
				"sectionNotes": [],
				"typeOfSection": 0,
				"lengthInSteps": 16,
				"altAnim": false,
				"mustHitSection": true,
				"changeBPM": false,
				"bpm": 150
			},
			{
				"sectionNotes": [],
				"typeOfSection": 0,
				"lengthInSteps": 16,
				"altAnim": false,
				"mustHitSection": true,
				"changeBPM": false,
				"bpm": 150
			},
			{
				"sectionNotes": [],
				"typeOfSection": 0,
				"lengthInSteps": 16,
				"altAnim": false,
				"mustHitSection": true,
				"changeBPM": false,
				"bpm": 150
			},
			{
				"sectionNotes": [],
				"typeOfSection": 0,
				"lengthInSteps": 16,
				"altAnim": false,
				"mustHitSection": true,
				"changeBPM": false,
				"bpm": 150
			},
			{
				"lengthInSteps": 16,
				"typeOfSection": 0,
				"sectionNotes": [],
				"altAnim": false,
				"bpm": 150,
				"changeBPM": false,
				"mustHitSection": true
			},
			{
				"lengthInSteps": 16,
				"typeOfSection": 0,
				"sectionNotes": [],
				"altAnim": false,
				"bpm": 150,
				"changeBPM": false,
				"mustHitSection": true
			},
			{
				"lengthInSteps": 16,
				"typeOfSection": 0,
				"sectionNotes": [],
				"altAnim": false,
				"bpm": 150,
				"changeBPM": false,
				"mustHitSection": true
			},
			{
				"lengthInSteps": 16,
				"typeOfSection": 0,
				"sectionNotes": [],
				"altAnim": false,
				"bpm": 150,
				"changeBPM": false,
				"mustHitSection": true
			},
			{
				"lengthInSteps": 16,
				"typeOfSection": 0,
				"sectionNotes": [],
				"altAnim": false,
				"bpm": 150,
				"changeBPM": false,
				"mustHitSection": true
			},
			{
				"lengthInSteps": 16,
				"typeOfSection": 0,
				"sectionNotes": [],
				"altAnim": false,
				"bpm": 150,
				"changeBPM": false,
				"mustHitSection": true
			},
			{
				"sectionNotes": [],
				"typeOfSection": 0,
				"lengthInSteps": 16,
				"altAnim": false,
				"mustHitSection": true,
				"changeBPM": false,
				"bpm": 150
			},
			{
				"sectionNotes": [],
				"typeOfSection": 0,
				"lengthInSteps": 16,
				"altAnim": false,
				"mustHitSection": true,
				"changeBPM": false,
				"bpm": 150
			},
			{
				"lengthInSteps": 16,
				"altAnim": false,
				"typeOfSection": 0,
				"sectionNotes": [],
				"bpm": 150,
				"changeBPM": false,
				"mustHitSection": true
			},
			{
				"lengthInSteps": 16,
				"altAnim": false,
				"typeOfSection": 0,
				"sectionNotes": [],
				"bpm": 150,
				"changeBPM": false,
				"mustHitSection": true
			},
			{
				"lengthInSteps": 16,
				"altAnim": false,
				"typeOfSection": 0,
				"sectionNotes": [],
				"bpm": 150,
				"changeBPM": false,
				"mustHitSection": true
			}
		],
		"player3": "gf",
		"isHey": false,
		"initialSpeed": 1.215,
		"cutsceneType": "none",
		"isSpooky": false,
		"song": "Sussus Toogus",
		"validScore": true,
		"speed": 2.7,
		"isMoody": false,
		"sectionLengths": [],
		"sliderVelocities": null,
		"sections": 0,
		"needsVoices": true,
		"stage": "toogus",
		"uiType": "normal",
		"bpm": 150,
		"gf": "gf"
	}
}